[
  {
    "id": "a3e83ab8-5084-492b-9802-10b0f54d160d",
    "created_at": "2024-04-13T03:08:48.786Z",
    "updated_at": "2023-07-15T05:05:33.904Z",
    "user_id": "ded464d7-7fbc-41d9-b600-1f5a934a99a8",
    "school_id": "a76eba8c-cf6c-40c2-a2a0-1e8a044e9d6d",
    "module_slug": "Service kappa process kappa omega dog omega the 1",
    "module_category": "Server platform beta",
    "is_started": true,
    "started_at": "2024-04-20T05:40:57.350Z",
    "is_completed": false,
    "completed_at": "2024-08-02T06:00:59.211Z",
    "sections_completed": 4464,
    "total_sections": 3928,
    "current_section": 9479,
    "time_spent_minutes": 3028,
    "is_bookmarked": true,
    "bookmarked_at": "2024-10-19T04:19:01.742Z",
    "user_notes": "Process brown epsilon alpha alpha gamma zeta omega",
    "metadata": "Omega brown zeta"
  },
  {
    "id": "651d897a-f2e3-48ed-85c7-1f8db1e4dfd3",
    "created_at": "2024-06-27T02:47:38.668Z",
    "updated_at": "2023-03-08T02:30:42.848Z",
    "user_id": "97193699-713c-47f8-8f10-d9439b2a445f",
    "school_id": "f1c813ca-b848-40f9-a525-ad503dbd4aec",
    "module_slug": "Epsilon fox platform data omega over lazy omega 2",
    "module_category": "Jumps client client",
    "is_started": true,
    "started_at": "2023-09-19T17:56:57.522Z",
    "is_completed": false,
    "completed_at": "2023-11-30T18:37:27.542Z",
    "sections_completed": 5319,
    "total_sections": 87842,
    "current_section": 2510,
    "time_spent_minutes": 3268,
    "is_bookmarked": false,
    "bookmarked_at": "2024-02-18T21:08:28.076Z",
    "user_notes": "Omega over gamma over beta omega gamma client",
    "metadata": "Network data lazy"
  },
  {
    "id": "acbd201e-decc-4cc4-81cb-bf4cdc530b86",
    "created_at": "2023-07-25T21:48:57.674Z",
    "updated_at": "2024-02-29T05:02:54.597Z",
    "user_id": "3f1b5745-f03c-42ce-b8d6-1dd68c86035f",
    "school_id": "e79eff17-079c-460e-9a26-f6b16b4cabdd",
    "module_slug": "Over module engine service platform brown module fox 3",
    "module_category": "Jumps brown lazy",
    "is_started": false,
    "started_at": "2024-11-18T02:03:21.995Z",
    "is_completed": false,
    "completed_at": "2023-08-30T17:32:18.100Z",
    "sections_completed": 9974,
    "total_sections": 84006,
    "current_section": 9608,
    "time_spent_minutes": 4824,
    "is_bookmarked": false,
    "bookmarked_at": "2024-03-04T21:55:27.561Z",
    "user_notes": "Kappa data beta beta module quick kappa brown",
    "metadata": "Omega epsilon brown"
  },
  {
    "id": "fb6d1b1e-7541-4574-b95e-05c8a4dfaf00",
    "created_at": "2023-11-13T19:18:38.285Z",
    "updated_at": "2023-07-22T10:23:50.813Z",
    "user_id": "355a62d3-deb2-4868-b22a-ee1e3d0bc083",
    "school_id": "6c2d5ecd-fa0e-4caf-bc6d-92cd359d8540",
    "module_slug": "Zeta server jumps over cloud client service fox 4",
    "module_category": "The lazy over",
    "is_started": true,
    "started_at": "2024-02-24T10:39:23.594Z",
    "is_completed": false,
    "completed_at": "2023-08-26T23:57:11.562Z",
    "sections_completed": 4417,
    "total_sections": 10778,
    "current_section": 5237,
    "time_spent_minutes": 6476,
    "is_bookmarked": false,
    "bookmarked_at": "2024-12-23T06:46:02.919Z",
    "user_notes": "Fox brown kappa process gamma quick data gamma",
    "metadata": "Sigma cloud sigma"
  },
  {
    "id": "c07bf869-b53d-4c6d-9014-9e36bcb78a26",
    "created_at": "2024-04-23T06:32:19.656Z",
    "updated_at": "2024-02-11T13:52:43.923Z",
    "user_id": "169de801-a34a-4139-a0c7-22b1926ed7fb",
    "school_id": "3757f878-24e4-4703-b9c7-b8ec4149f18d",
    "module_slug": "Epsilon jumps omega dog fox module cloud fox 5",
    "module_category": "Delta sigma lambda",
    "is_started": true,
    "started_at": "2023-04-09T18:11:52.660Z",
    "is_completed": false,
    "completed_at": "2024-06-06T17:10:06.498Z",
    "sections_completed": 3521,
    "total_sections": 58952,
    "current_section": 2813,
    "time_spent_minutes": 9740,
    "is_bookmarked": false,
    "bookmarked_at": "2023-11-01T09:18:09.744Z",
    "user_notes": "Delta platform kappa server gamma delta service epsilon",
    "metadata": "Cloud epsilon alpha"
  },
  {
    "id": "07a90693-ccbc-4319-b9fe-6306f8834a17",
    "created_at": "2024-01-28T14:38:35.290Z",
    "updated_at": "2024-11-26T15:26:42.561Z",
    "user_id": "b1b8cdc7-d37a-49c1-aafc-7e8c158cb8b5",
    "school_id": "6a2807e4-3c6c-40cb-a83a-947f8f0d0f9c",
    "module_slug": "System alpha jumps beta brown fox the lazy 6",
    "module_category": "Jumps the engine",
    "is_started": true,
    "started_at": "2024-06-17T06:34:15.089Z",
    "is_completed": true,
    "completed_at": "2023-06-18T11:05:14.043Z",
    "sections_completed": 8334,
    "total_sections": 95649,
    "current_section": 1097,
    "time_spent_minutes": 8387,
    "is_bookmarked": false,
    "bookmarked_at": "2023-04-25T00:47:51.944Z",
    "user_notes": "Platform cloud process cloud omega data zeta beta",
    "metadata": "Fox omega lazy"
  },
  {
    "id": "52f1a9cd-165a-47c9-9400-d9b067be2a19",
    "created_at": "2024-07-21T05:06:43.880Z",
    "updated_at": "2024-02-26T17:16:41.193Z",
    "user_id": "77409a2e-fa26-4040-ab51-b054a6d62520",
    "school_id": "30d77862-a014-44ce-983e-e8a05cdcc1b3",
    "module_slug": "Process brown beta the lazy process alpha kappa 7",
    "module_category": "Process engine cloud",
    "is_started": false,
    "started_at": "2023-06-11T08:27:07.001Z",
    "is_completed": true,
    "completed_at": "2023-12-05T12:52:09.132Z",
    "sections_completed": 8132,
    "total_sections": 75507,
    "current_section": 7310,
    "time_spent_minutes": 1019,
    "is_bookmarked": true,
    "bookmarked_at": "2023-06-20T12:15:09.315Z",
    "user_notes": "Brown fox process platform lazy jumps omega beta",
    "metadata": "Service jumps gamma"
  },
  {
    "id": "f7a9dd66-d132-4b4d-8eda-8ccdf3a0d95e",
    "created_at": "2023-09-11T17:51:39.983Z",
    "updated_at": "2024-10-08T10:19:40.673Z",
    "user_id": "170e7a28-0cc9-4363-a4a7-3406bdd02696",
    "school_id": "3e8952a5-f212-47c5-9e34-9453ab8fecdd",
    "module_slug": "Service beta system client beta zeta cloud beta 8",
    "module_category": "Sigma jumps alpha",
    "is_started": false,
    "started_at": "2024-12-20T02:39:54.362Z",
    "is_completed": false,
    "completed_at": "2024-03-18T16:44:23.514Z",
    "sections_completed": 973,
    "total_sections": 63355,
    "current_section": 9351,
    "time_spent_minutes": 1354,
    "is_bookmarked": false,
    "bookmarked_at": "2024-03-16T20:52:15.398Z",
    "user_notes": "Epsilon data zeta gamma lambda dog gamma system",
    "metadata": "Brown over cloud"
  },
  {
    "id": "80492dbf-d2d0-4d91-a15b-309a68ead4ca",
    "created_at": "2024-08-09T01:07:59.804Z",
    "updated_at": "2024-10-31T00:08:21.472Z",
    "user_id": "9e960472-64ad-4619-93b1-10133b3710a7",
    "school_id": "769be8e4-a3c5-4917-8be9-4e9220a57e3d",
    "module_slug": "Server lazy module jumps data platform cloud module 9",
    "module_category": "Data delta gamma",
    "is_started": false,
    "started_at": "2023-01-23T13:51:54.889Z",
    "is_completed": false,
    "completed_at": "2023-06-08T19:40:23.530Z",
    "sections_completed": 4023,
    "total_sections": 94652,
    "current_section": 9064,
    "time_spent_minutes": 7175,
    "is_bookmarked": false,
    "bookmarked_at": "2023-03-22T07:50:11.187Z",
    "user_notes": "Lambda theta service cloud dog kappa epsilon zeta",
    "metadata": "Platform server delta"
  },
  {
    "id": "54030e26-7a06-4ee7-b526-d45e8000eec1",
    "created_at": "2024-05-13T14:48:48.665Z",
    "updated_at": "2023-05-27T02:00:34.268Z",
    "user_id": "29da9308-02a7-44b3-a3bf-a260989bd93c",
    "school_id": "36a66c02-6a0c-46da-ad01-970e20511e13",
    "module_slug": "Alpha alpha alpha delta epsilon data process delta 10",
    "module_category": "Beta kappa fox",
    "is_started": true,
    "started_at": "2024-05-28T10:21:53.811Z",
    "is_completed": true,
    "completed_at": "2024-02-09T15:32:07.329Z",
    "sections_completed": 9505,
    "total_sections": 61107,
    "current_section": 382,
    "time_spent_minutes": 2697,
    "is_bookmarked": true,
    "bookmarked_at": "2024-05-20T00:30:25.206Z",
    "user_notes": "Jumps delta brown service delta client zeta client",
    "metadata": "The service brown"
  },
  {
    "id": "285658de-6861-4a41-93cd-b5d39b141742",
    "created_at": "2024-09-29T20:05:23.346Z",
    "updated_at": "2024-04-19T09:22:00.954Z",
    "user_id": "170e7a28-0cc9-4363-a4a7-3406bdd02696",
    "school_id": "95d56d72-c51f-4111-bdc3-b3a7dc6033e0",
    "module_slug": "Network engine fox lambda kappa beta lazy fox 11",
    "module_category": "Beta lazy platform",
    "is_started": true,
    "started_at": "2023-10-22T17:25:04.997Z",
    "is_completed": false,
    "completed_at": "2024-07-04T17:42:07.241Z",
    "sections_completed": 5524,
    "total_sections": 59025,
    "current_section": 6723,
    "time_spent_minutes": 2626,
    "is_bookmarked": false,
    "bookmarked_at": "2023-05-28T03:01:19.185Z",
    "user_notes": "Cloud quick module platform server jumps client zeta",
    "metadata": "System jumps the"
  },
  {
    "id": "8a202f05-adf8-49d4-b7c5-7dc8500f52d1",
    "created_at": "2023-07-18T00:51:17.067Z",
    "updated_at": "2023-11-18T11:36:31.061Z",
    "user_id": "a10e1f0e-342b-4a00-824e-0709f6de5dab",
    "school_id": "ca622101-e857-428f-bbf6-3cff8789d201",
    "module_slug": "Brown quick client engine brown data data lambda 12",
    "module_category": "Lambda lambda zeta",
    "is_started": true,
    "started_at": "2023-04-14T15:32:52.412Z",
    "is_completed": true,
    "completed_at": "2023-05-20T22:32:45.391Z",
    "sections_completed": 6700,
    "total_sections": 22875,
    "current_section": 7120,
    "time_spent_minutes": 1796,
    "is_bookmarked": false,
    "bookmarked_at": "2023-04-22T09:02:29.000Z",
    "user_notes": "Module jumps sigma dog delta theta engine dog",
    "metadata": "Dog network cloud"
  },
  {
    "id": "017ecf70-f00b-46e7-8d71-00d2668f72f1",
    "created_at": "2023-02-18T07:42:01.072Z",
    "updated_at": "2024-03-22T18:36:48.695Z",
    "user_id": "93d6fc35-a3f2-4c17-aacb-929aa6aa2fc5",
    "school_id": "00109f6c-9a53-47c0-9e33-587bdf00bf4d",
    "module_slug": "Brown engine cloud lambda the module platform platform 13",
    "module_category": "Gamma system sigma",
    "is_started": false,
    "started_at": "2023-06-02T18:48:04.328Z",
    "is_completed": true,
    "completed_at": "2023-11-05T07:58:39.403Z",
    "sections_completed": 3943,
    "total_sections": 49473,
    "current_section": 4284,
    "time_spent_minutes": 9131,
    "is_bookmarked": false,
    "bookmarked_at": "2023-12-18T12:32:46.484Z",
    "user_notes": "Lazy server zeta service module beta lazy process",
    "metadata": "Theta server process"
  },
  {
    "id": "f47c3f32-87df-4932-a9b9-c1154cd44485",
    "created_at": "2023-08-10T14:01:10.604Z",
    "updated_at": "2023-07-31T05:34:30.600Z",
    "user_id": "e32797c0-a915-4001-a33c-fec119eb8fdf",
    "school_id": "a22f4242-5c63-4c92-b09b-3a83acf9e2e4",
    "module_slug": "Alpha beta client kappa delta the zeta platform 14",
    "module_category": "The platform epsilon",
    "is_started": true,
    "started_at": "2023-05-19T23:20:11.198Z",
    "is_completed": false,
    "completed_at": "2024-07-30T21:10:24.037Z",
    "sections_completed": 7736,
    "total_sections": 26453,
    "current_section": 7925,
    "time_spent_minutes": 4613,
    "is_bookmarked": true,
    "bookmarked_at": "2023-02-03T20:47:09.777Z",
    "user_notes": "Data kappa over process over dog brown lazy",
    "metadata": "Dog sigma jumps"
  },
  {
    "id": "ed8a2a7a-6e47-426d-bd2f-f01527831ade",
    "created_at": "2024-05-12T18:03:34.268Z",
    "updated_at": "2024-12-25T17:27:07.150Z",
    "user_id": "169de801-a34a-4139-a0c7-22b1926ed7fb",
    "school_id": "51447bfd-fb7b-49bb-8117-0624e086e562",
    "module_slug": "Epsilon quick gamma kappa cloud the server module 15",
    "module_category": "Engine alpha network",
    "is_started": false,
    "started_at": "2023-05-04T13:47:26.765Z",
    "is_completed": true,
    "completed_at": "2024-05-02T08:27:50.762Z",
    "sections_completed": 4339,
    "total_sections": 39902,
    "current_section": 4538,
    "time_spent_minutes": 9429,
    "is_bookmarked": false,
    "bookmarked_at": "2024-11-23T02:37:03.512Z",
    "user_notes": "Fox lambda gamma brown fox process jumps lazy",
    "metadata": "Engine zeta the"
  },
  {
    "id": "fc3b7863-8764-4981-9198-37b72f581cbf",
    "created_at": "2024-06-04T16:35:45.646Z",
    "updated_at": "2023-10-20T04:51:58.458Z",
    "user_id": "7b7d1f6f-7f60-4a82-8c29-f4fb6fb41535",
    "school_id": "6c2d5ecd-fa0e-4caf-bc6d-92cd359d8540",
    "module_slug": "Module client system process fox system process service 16",
    "module_category": "Network epsilon data",
    "is_started": false,
    "started_at": "2024-04-10T22:57:28.026Z",
    "is_completed": false,
    "completed_at": "2023-10-04T17:03:31.654Z",
    "sections_completed": 6057,
    "total_sections": 15809,
    "current_section": 9028,
    "time_spent_minutes": 7277,
    "is_bookmarked": true,
    "bookmarked_at": "2024-11-26T00:26:09.064Z",
    "user_notes": "Zeta cloud jumps fox kappa network omega network",
    "metadata": "Network process module"
  },
  {
    "id": "a43b76f5-5084-48b2-9c34-b70491345335",
    "created_at": "2023-11-16T23:55:52.186Z",
    "updated_at": "2024-07-24T03:36:03.809Z",
    "user_id": "431a5b40-2048-4f3c-8be1-4f5051034b34",
    "school_id": "d1e20847-18b5-4dd4-b591-dea6f83b635a",
    "module_slug": "Brown platform quick over epsilon jumps zeta platform 17",
    "module_category": "The cloud zeta",
    "is_started": true,
    "started_at": "2023-12-18T18:29:23.930Z",
    "is_completed": true,
    "completed_at": "2024-11-07T14:36:38.740Z",
    "sections_completed": 6165,
    "total_sections": 80037,
    "current_section": 7195,
    "time_spent_minutes": 349,
    "is_bookmarked": false,
    "bookmarked_at": "2024-10-14T05:42:02.753Z",
    "user_notes": "System kappa lambda system delta dog alpha dog",
    "metadata": "Sigma the the"
  },
  {
    "id": "13335ea9-af53-42b2-9580-b164f8e7dbd3",
    "created_at": "2023-06-14T08:40:30.943Z",
    "updated_at": "2024-04-06T17:02:14.644Z",
    "user_id": "9e960472-64ad-4619-93b1-10133b3710a7",
    "school_id": "7f1a6162-0c95-498f-b977-567d263d0836",
    "module_slug": "Fox system dog service over sigma platform data 18",
    "module_category": "Fox over engine",
    "is_started": false,
    "started_at": "2023-04-09T02:31:02.864Z",
    "is_completed": true,
    "completed_at": "2023-09-13T10:25:37.828Z",
    "sections_completed": 2454,
    "total_sections": 96526,
    "current_section": 4958,
    "time_spent_minutes": 8439,
    "is_bookmarked": true,
    "bookmarked_at": "2023-10-05T11:52:04.991Z",
    "user_notes": "Jumps dog service sigma data gamma alpha epsilon",
    "metadata": "Gamma delta kappa"
  },
  {
    "id": "20f7806f-946d-4d29-9228-385206bb9820",
    "created_at": "2024-09-29T22:06:09.808Z",
    "updated_at": "2023-06-16T08:04:50.170Z",
    "user_id": "68a7b7c2-d0de-4752-af9a-260157f65f43",
    "school_id": "1da2e8b3-b68b-4d22-a3ab-d7db4b2e932b",
    "module_slug": "Cloud server zeta client kappa delta system brown 19",
    "module_category": "Module client fox",
    "is_started": false,
    "started_at": "2023-11-15T03:25:16.161Z",
    "is_completed": false,
    "completed_at": "2024-08-10T10:19:21.461Z",
    "sections_completed": 1089,
    "total_sections": 25122,
    "current_section": 6356,
    "time_spent_minutes": 9914,
    "is_bookmarked": false,
    "bookmarked_at": "2023-08-30T19:28:51.230Z",
    "user_notes": "Sigma client over jumps service epsilon omega platform",
    "metadata": "The beta the"
  },
  {
    "id": "984b9ffd-7a3b-4957-a851-56f1a4082125",
    "created_at": "2024-06-05T19:07:02.961Z",
    "updated_at": "2024-01-25T06:15:07.221Z",
    "user_id": "170e7a28-0cc9-4363-a4a7-3406bdd02696",
    "school_id": "a8414277-0b30-44cc-82f6-fa46c4b1eb54",
    "module_slug": "Data brown client fox fox epsilon lazy sigma 20",
    "module_category": "Sigma module jumps",
    "is_started": true,
    "started_at": "2024-07-30T09:30:54.434Z",
    "is_completed": false,
    "completed_at": "2023-10-03T00:10:38.093Z",
    "sections_completed": 3975,
    "total_sections": 99776,
    "current_section": 6134,
    "time_spent_minutes": 7183,
    "is_bookmarked": true,
    "bookmarked_at": "2023-10-26T01:05:21.719Z",
    "user_notes": "Dog lazy network data quick alpha the lambda",
    "metadata": "Zeta fox platform"
  },
  {
    "id": "f35d8e9f-91a1-4a63-a448-03fbcc1c7c55",
    "created_at": "2023-10-14T00:10:21.510Z",
    "updated_at": "2023-03-25T04:49:43.536Z",
    "user_id": "f7c14361-afba-457f-90e6-2cb012c03d91",
    "school_id": "3757f878-24e4-4703-b9c7-b8ec4149f18d",
    "module_slug": "Engine quick beta fox epsilon engine theta engine 21",
    "module_category": "Over zeta cloud",
    "is_started": false,
    "started_at": "2024-01-14T23:57:27.202Z",
    "is_completed": true,
    "completed_at": "2024-06-15T01:52:00.146Z",
    "sections_completed": 3788,
    "total_sections": 93111,
    "current_section": 7373,
    "time_spent_minutes": 5057,
    "is_bookmarked": true,
    "bookmarked_at": "2023-01-24T02:02:35.050Z",
    "user_notes": "Over sigma zeta engine quick kappa data dog",
    "metadata": "Process process theta"
  },
  {
    "id": "840fb6c0-9867-45ed-87b9-69c2ab66e35e",
    "created_at": "2023-01-28T14:18:20.039Z",
    "updated_at": "2023-04-23T18:18:02.345Z",
    "user_id": "751f3d7c-ff2a-479c-b212-6d1ddd456452",
    "school_id": "9d02df2f-9196-4af3-925a-369b879cebc9",
    "module_slug": "Zeta omega module fox lambda epsilon client engine 22",
    "module_category": "Omega theta delta",
    "is_started": false,
    "started_at": "2023-07-24T00:17:27.380Z",
    "is_completed": false,
    "completed_at": "2023-08-23T21:30:33.803Z",
    "sections_completed": 3541,
    "total_sections": 58341,
    "current_section": 8864,
    "time_spent_minutes": 8432,
    "is_bookmarked": true,
    "bookmarked_at": "2024-05-09T16:30:45.189Z",
    "user_notes": "Service beta the theta module service system sigma",
    "metadata": "Zeta epsilon gamma"
  },
  {
    "id": "cc67743b-f523-4d91-b022-c3b8834968ad",
    "created_at": "2024-09-22T20:18:52.948Z",
    "updated_at": "2024-06-29T09:17:52.704Z",
    "user_id": "ce67985f-24c5-4c89-b6ca-4ba33ee65661",
    "school_id": "6c2d5ecd-fa0e-4caf-bc6d-92cd359d8540",
    "module_slug": "Service network gamma epsilon lazy delta quick jumps 23",
    "module_category": "Delta engine gamma",
    "is_started": false,
    "started_at": "2024-04-05T08:52:42.867Z",
    "is_completed": true,
    "completed_at": "2023-07-17T22:13:10.790Z",
    "sections_completed": 926,
    "total_sections": 31359,
    "current_section": 9631,
    "time_spent_minutes": 5637,
    "is_bookmarked": true,
    "bookmarked_at": "2024-11-23T22:55:47.367Z",
    "user_notes": "Delta platform delta lazy kappa lambda the dog",
    "metadata": "Module system theta"
  },
  {
    "id": "f1d52697-40fe-4385-81ac-27c0e2978a3d",
    "created_at": "2023-09-13T17:37:19.206Z",
    "updated_at": "2023-04-16T10:57:38.955Z",
    "user_id": "51f8ba45-72f2-4f48-9457-dbc8135ee7a3",
    "school_id": "72862cd1-b7dc-4fe1-a248-87852f1474d5",
    "module_slug": "Delta system module cloud quick epsilon omega lambda 24",
    "module_category": "Data platform brown",
    "is_started": false,
    "started_at": "2024-10-09T22:39:34.861Z",
    "is_completed": true,
    "completed_at": "2024-06-23T21:45:23.730Z",
    "sections_completed": 9882,
    "total_sections": 85978,
    "current_section": 9529,
    "time_spent_minutes": 4691,
    "is_bookmarked": true,
    "bookmarked_at": "2024-09-08T18:56:32.263Z",
    "user_notes": "Omega omega brown process sigma theta network platform",
    "metadata": "Process cloud sigma"
  },
  {
    "id": "a8bc4d9b-c835-4518-91a9-b171639957bb",
    "created_at": "2023-08-03T04:15:11.975Z",
    "updated_at": "2024-12-18T21:38:03.203Z",
    "user_id": "6090c86d-d922-4d47-96db-1835cf3bf57e",
    "school_id": "51447bfd-fb7b-49bb-8117-0624e086e562",
    "module_slug": "Dog brown server sigma jumps alpha network kappa 25",
    "module_category": "Sigma delta theta",
    "is_started": false,
    "started_at": "2023-02-20T19:16:48.080Z",
    "is_completed": true,
    "completed_at": "2024-10-20T06:37:29.249Z",
    "sections_completed": 7209,
    "total_sections": 37461,
    "current_section": 4783,
    "time_spent_minutes": 3489,
    "is_bookmarked": true,
    "bookmarked_at": "2024-08-22T14:49:34.421Z",
    "user_notes": "Gamma fox network data omega data platform jumps",
    "metadata": "Lazy network zeta"
  },
  {
    "id": "f70c1801-bf30-4698-be8d-d83259e30658",
    "created_at": "2023-08-16T22:09:39.599Z",
    "updated_at": "2023-02-27T03:57:33.862Z",
    "user_id": "a3ac05b6-03cd-4cc9-a028-054b5b79b736",
    "school_id": "d1e20847-18b5-4dd4-b591-dea6f83b635a",
    "module_slug": "Cloud alpha sigma brown gamma lazy the network 26",
    "module_category": "Alpha gamma epsilon",
    "is_started": true,
    "started_at": "2023-05-19T09:24:14.552Z",
    "is_completed": false,
    "completed_at": "2023-08-28T18:44:40.360Z",
    "sections_completed": 5043,
    "total_sections": 4428,
    "current_section": 3978,
    "time_spent_minutes": 4691,
    "is_bookmarked": false,
    "bookmarked_at": "2023-02-20T19:33:06.709Z",
    "user_notes": "Epsilon engine module sigma cloud the system service",
    "metadata": "Gamma network quick"
  },
  {
    "id": "25019c0c-d1ce-4195-ab9f-c8c8718e4428",
    "created_at": "2023-06-28T05:40:13.245Z",
    "updated_at": "2024-02-08T11:16:04.515Z",
    "user_id": "a5076835-a146-407a-95fc-0c07e3ae44a8",
    "school_id": "7605aa96-616f-4ad8-a80d-94ec54b2aa51",
    "module_slug": "Brown process jumps network fox brown service platform 27",
    "module_category": "Delta kappa process",
    "is_started": false,
    "started_at": "2023-06-29T14:11:31.334Z",
    "is_completed": true,
    "completed_at": "2024-05-23T17:43:06.252Z",
    "sections_completed": 800,
    "total_sections": 10449,
    "current_section": 4592,
    "time_spent_minutes": 5525,
    "is_bookmarked": false,
    "bookmarked_at": "2023-03-06T14:47:21.159Z",
    "user_notes": "Quick data zeta zeta kappa fox data the",
    "metadata": "Brown quick omega"
  },
  {
    "id": "7db909e5-a5d2-4d8f-ab70-59f8d39b0912",
    "created_at": "2023-04-21T00:24:42.387Z",
    "updated_at": "2024-08-16T13:57:00.665Z",
    "user_id": "53031b80-974a-46fc-a146-c37e7c5b5844",
    "school_id": "a8414277-0b30-44cc-82f6-fa46c4b1eb54",
    "module_slug": "Jumps the beta jumps service over jumps network 28",
    "module_category": "Lambda lazy theta",
    "is_started": false,
    "started_at": "2023-08-24T13:15:14.038Z",
    "is_completed": false,
    "completed_at": "2023-03-06T20:31:52.706Z",
    "sections_completed": 8341,
    "total_sections": 27598,
    "current_section": 1086,
    "time_spent_minutes": 4979,
    "is_bookmarked": true,
    "bookmarked_at": "2023-02-02T20:26:53.012Z",
    "user_notes": "Module engine jumps server cloud theta lambda epsilon",
    "metadata": "Server lambda beta"
  },
  {
    "id": "dfde3aed-0b28-46bf-969a-6c49797c34ad",
    "created_at": "2023-08-04T03:49:53.069Z",
    "updated_at": "2023-11-12T16:41:13.476Z",
    "user_id": "355a62d3-deb2-4868-b22a-ee1e3d0bc083",
    "school_id": "fa4a14da-1fca-487a-823a-bb45fa95e2aa",
    "module_slug": "The sigma engine epsilon kappa the process omega 29",
    "module_category": "Over zeta alpha",
    "is_started": false,
    "started_at": "2023-03-11T05:53:53.054Z",
    "is_completed": true,
    "completed_at": "2023-10-31T19:05:16.566Z",
    "sections_completed": 5052,
    "total_sections": 82922,
    "current_section": 8419,
    "time_spent_minutes": 1025,
    "is_bookmarked": false,
    "bookmarked_at": "2024-07-03T20:28:10.605Z",
    "user_notes": "Platform alpha network alpha alpha jumps client jumps",
    "metadata": "Brown lazy omega"
  },
  {
    "id": "d31f9123-c121-4e63-8f20-38ff37f1f5b2",
    "created_at": "2023-07-15T08:31:44.304Z",
    "updated_at": "2023-01-11T11:35:33.414Z",
    "user_id": "169de801-a34a-4139-a0c7-22b1926ed7fb",
    "school_id": "49871cfe-155b-4956-9609-038c92155cdd",
    "module_slug": "System brown over lambda lambda lambda sigma beta 30",
    "module_category": "Over over theta",
    "is_started": false,
    "started_at": "2024-10-08T04:22:56.149Z",
    "is_completed": false,
    "completed_at": "2024-11-25T14:50:08.473Z",
    "sections_completed": 4934,
    "total_sections": 35594,
    "current_section": 3859,
    "time_spent_minutes": 7348,
    "is_bookmarked": false,
    "bookmarked_at": "2024-09-09T21:59:06.788Z",
    "user_notes": "Zeta process client lazy beta module system system",
    "metadata": "Engine service engine"
  },
  {
    "id": "6702dd36-646c-4a58-8080-e44392af6ae4",
    "created_at": "2024-02-18T05:13:53.492Z",
    "updated_at": "2024-11-15T22:38:22.254Z",
    "user_id": "256d52d9-02cd-4cdd-bbff-d4c496410840",
    "school_id": "ca622101-e857-428f-bbf6-3cff8789d201",
    "module_slug": "Sigma brown sigma over omega system sigma quick 31",
    "module_category": "Sigma delta gamma",
    "is_started": true,
    "started_at": "2024-01-23T16:20:38.948Z",
    "is_completed": true,
    "completed_at": "2023-04-13T13:51:58.568Z",
    "sections_completed": 1733,
    "total_sections": 10173,
    "current_section": 3728,
    "time_spent_minutes": 2118,
    "is_bookmarked": false,
    "bookmarked_at": "2023-03-06T10:17:33.398Z",
    "user_notes": "Client gamma dog module process brown dog the",
    "metadata": "Network brown quick"
  },
  {
    "id": "736f6381-e0df-46c6-b8c0-dac0f87786d6",
    "created_at": "2023-12-21T21:36:55.010Z",
    "updated_at": "2023-08-04T04:47:34.052Z",
    "user_id": "6cd587fc-8a79-47ca-875c-d813acfd99a0",
    "school_id": "1da2e8b3-b68b-4d22-a3ab-d7db4b2e932b",
    "module_slug": "Theta quick platform sigma omega delta process lazy 32",
    "module_category": "Cloud network theta",
    "is_started": false,
    "started_at": "2024-04-18T03:36:02.441Z",
    "is_completed": true,
    "completed_at": "2023-09-02T04:57:07.057Z",
    "sections_completed": 7856,
    "total_sections": 78879,
    "current_section": 7398,
    "time_spent_minutes": 1011,
    "is_bookmarked": false,
    "bookmarked_at": "2023-04-17T03:30:11.330Z",
    "user_notes": "Sigma omega cloud process data beta system fox",
    "metadata": "Omega system data"
  },
  {
    "id": "5ee1e800-0d11-4927-a12a-08354f703c56",
    "created_at": "2023-07-19T18:56:34.375Z",
    "updated_at": "2023-07-03T18:25:43.899Z",
    "user_id": "a2771903-64cf-4fca-b15d-48ef2dc43dff",
    "school_id": "3e8952a5-f212-47c5-9e34-9453ab8fecdd",
    "module_slug": "Over service network sigma brown lazy client the 33",
    "module_category": "Over lambda quick",
    "is_started": true,
    "started_at": "2024-11-11T00:42:46.471Z",
    "is_completed": true,
    "completed_at": "2024-03-11T20:19:55.280Z",
    "sections_completed": 8084,
    "total_sections": 58017,
    "current_section": 5209,
    "time_spent_minutes": 2096,
    "is_bookmarked": false,
    "bookmarked_at": "2024-03-27T12:24:04.409Z",
    "user_notes": "Delta dog sigma over gamma epsilon network process",
    "metadata": "Module engine lambda"
  },
  {
    "id": "a1e511c2-fd2d-4060-9a27-cba53d522f3c",
    "created_at": "2023-11-26T20:40:31.977Z",
    "updated_at": "2024-06-25T20:12:44.839Z",
    "user_id": "355a62d3-deb2-4868-b22a-ee1e3d0bc083",
    "school_id": "7ae13493-f756-4fb3-8d49-9fe9d91476ec",
    "module_slug": "System process network quick server sigma cloud client 34",
    "module_category": "Theta theta alpha",
    "is_started": false,
    "started_at": "2023-09-11T10:06:34.265Z",
    "is_completed": true,
    "completed_at": "2024-02-20T01:05:49.081Z",
    "sections_completed": 4305,
    "total_sections": 29582,
    "current_section": 9490,
    "time_spent_minutes": 239,
    "is_bookmarked": false,
    "bookmarked_at": "2024-02-22T06:07:45.749Z",
    "user_notes": "Jumps dog dog gamma lazy zeta cloud process",
    "metadata": "Brown lazy over"
  },
  {
    "id": "b0d85f56-467d-4e64-8320-1e3f37cd4d50",
    "created_at": "2024-04-11T16:14:51.577Z",
    "updated_at": "2024-03-14T23:52:02.946Z",
    "user_id": "4464c5fc-c1be-4bbc-9368-dc6cf5cb9193",
    "school_id": "00109f6c-9a53-47c0-9e33-587bdf00bf4d",
    "module_slug": "Module network sigma lambda alpha jumps platform alpha 35",
    "module_category": "Server sigma platform",
    "is_started": false,
    "started_at": "2023-11-05T00:18:31.205Z",
    "is_completed": true,
    "completed_at": "2023-06-24T08:14:59.032Z",
    "sections_completed": 7772,
    "total_sections": 28663,
    "current_section": 3665,
    "time_spent_minutes": 6067,
    "is_bookmarked": false,
    "bookmarked_at": "2024-05-21T14:21:32.925Z",
    "user_notes": "Platform beta engine server zeta client data lambda",
    "metadata": "Lambda platform dog"
  },
  {
    "id": "b6be01c2-b01b-4570-93ab-520027d13056",
    "created_at": "2023-05-21T10:36:30.507Z",
    "updated_at": "2023-05-16T14:19:54.947Z",
    "user_id": "3f1b5745-f03c-42ce-b8d6-1dd68c86035f",
    "school_id": "30d77862-a014-44ce-983e-e8a05cdcc1b3",
    "module_slug": "Server the process epsilon module platform client kappa 36",
    "module_category": "Sigma over quick",
    "is_started": true,
    "started_at": "2024-12-02T14:34:49.599Z",
    "is_completed": true,
    "completed_at": "2024-06-23T07:12:20.015Z",
    "sections_completed": 2628,
    "total_sections": 3848,
    "current_section": 9058,
    "time_spent_minutes": 8215,
    "is_bookmarked": false,
    "bookmarked_at": "2024-09-04T11:09:57.926Z",
    "user_notes": "Dog system process brown epsilon the zeta alpha",
    "metadata": "Client delta data"
  },
  {
    "id": "6f66920b-4521-4101-95ef-b586c5c82a90",
    "created_at": "2023-10-04T06:00:29.028Z",
    "updated_at": "2024-03-24T19:27:08.484Z",
    "user_id": "ea65d9c9-c9e0-4af9-9aef-2a2ec0fd37f4",
    "school_id": "302e57f3-f396-4a47-a165-7dcc583d2e9b",
    "module_slug": "Sigma engine cloud fox process platform process server 37",
    "module_category": "Omega epsilon data",
    "is_started": false,
    "started_at": "2024-08-18T21:50:33.860Z",
    "is_completed": false,
    "completed_at": "2024-02-07T13:09:44.667Z",
    "sections_completed": 6285,
    "total_sections": 30102,
    "current_section": 6887,
    "time_spent_minutes": 6448,
    "is_bookmarked": true,
    "bookmarked_at": "2024-12-18T06:40:41.582Z",
    "user_notes": "Omega dog theta alpha dog quick omega platform",
    "metadata": "Module omega service"
  },
  {
    "id": "c66e1a6c-09d0-473d-9f74-65a7917b8dbe",
    "created_at": "2024-06-21T17:09:58.897Z",
    "updated_at": "2024-01-10T08:11:56.603Z",
    "user_id": "b1b8cdc7-d37a-49c1-aafc-7e8c158cb8b5",
    "school_id": "1da2e8b3-b68b-4d22-a3ab-d7db4b2e932b",
    "module_slug": "System server beta dog server server zeta gamma 38",
    "module_category": "Omega epsilon network",
    "is_started": false,
    "started_at": "2023-08-23T04:31:15.496Z",
    "is_completed": true,
    "completed_at": "2023-04-20T23:31:39.628Z",
    "sections_completed": 5047,
    "total_sections": 92163,
    "current_section": 3331,
    "time_spent_minutes": 2339,
    "is_bookmarked": false,
    "bookmarked_at": "2024-01-10T23:43:04.825Z",
    "user_notes": "Client lazy alpha lambda system service brown epsilon",
    "metadata": "Cloud beta omega"
  },
  {
    "id": "62293172-88a6-445f-93c4-cff37c16169d",
    "created_at": "2023-05-09T16:33:32.420Z",
    "updated_at": "2023-03-23T21:47:18.940Z",
    "user_id": "a10e1f0e-342b-4a00-824e-0709f6de5dab",
    "school_id": "e63ae94b-1898-4c17-ade8-2906c177e61b",
    "module_slug": "System the lambda alpha platform omega platform sigma 39",
    "module_category": "Brown over beta",
    "is_started": false,
    "started_at": "2024-05-01T00:30:01.490Z",
    "is_completed": false,
    "completed_at": "2024-11-16T16:53:08.579Z",
    "sections_completed": 4735,
    "total_sections": 60231,
    "current_section": 7367,
    "time_spent_minutes": 1495,
    "is_bookmarked": false,
    "bookmarked_at": "2023-09-01T06:53:28.804Z",
    "user_notes": "Server delta network lazy the gamma epsilon omega",
    "metadata": "Sigma lazy jumps"
  },
  {
    "id": "6f46c6ed-0457-4d77-8f8c-954efbb963e1",
    "created_at": "2023-03-13T11:45:12.939Z",
    "updated_at": "2024-11-05T02:41:37.700Z",
    "user_id": "fa815b97-5899-4e6c-88b0-91d5046743e0",
    "school_id": "a8414277-0b30-44cc-82f6-fa46c4b1eb54",
    "module_slug": "Dog jumps client zeta process data gamma over 40",
    "module_category": "Cloud omega client",
    "is_started": true,
    "started_at": "2024-04-08T09:43:55.304Z",
    "is_completed": false,
    "completed_at": "2024-11-07T19:35:58.639Z",
    "sections_completed": 8123,
    "total_sections": 55617,
    "current_section": 3962,
    "time_spent_minutes": 8354,
    "is_bookmarked": true,
    "bookmarked_at": "2023-12-02T14:29:12.030Z",
    "user_notes": "Brown dog system delta network platform over zeta",
    "metadata": "Sigma system dog"
  },
  {
    "id": "7b436e34-9966-4f98-9336-a795e11fe076",
    "created_at": "2024-01-19T05:23:27.654Z",
    "updated_at": "2024-02-14T01:35:56.729Z",
    "user_id": "169de801-a34a-4139-a0c7-22b1926ed7fb",
    "school_id": "3ba5f8eb-68c8-4e45-9dfa-9c18cb043f51",
    "module_slug": "Over zeta server lazy server network omega lazy 41",
    "module_category": "Service system dog",
    "is_started": true,
    "started_at": "2024-08-27T17:10:57.967Z",
    "is_completed": false,
    "completed_at": "2023-09-20T01:48:54.291Z",
    "sections_completed": 2223,
    "total_sections": 72805,
    "current_section": 2960,
    "time_spent_minutes": 1587,
    "is_bookmarked": false,
    "bookmarked_at": "2024-04-24T08:38:24.905Z",
    "user_notes": "Engine service gamma alpha fox quick brown cloud",
    "metadata": "Jumps lazy module"
  },
  {
    "id": "0097bcd7-6772-4ca2-8ba0-1b79b08e5880",
    "created_at": "2024-03-12T03:11:51.277Z",
    "updated_at": "2023-06-26T15:16:32.041Z",
    "user_id": "311ed5e5-7033-4f3a-8522-bc4773e4b14a",
    "school_id": "36a66c02-6a0c-46da-ad01-970e20511e13",
    "module_slug": "Delta system jumps alpha system beta lambda dog 42",
    "module_category": "Epsilon quick delta",
    "is_started": false,
    "started_at": "2023-02-09T16:36:09.478Z",
    "is_completed": true,
    "completed_at": "2024-06-20T22:15:23.836Z",
    "sections_completed": 2328,
    "total_sections": 84099,
    "current_section": 5171,
    "time_spent_minutes": 3964,
    "is_bookmarked": false,
    "bookmarked_at": "2023-08-01T14:50:08.630Z",
    "user_notes": "Gamma quick alpha network client lazy service gamma",
    "metadata": "Lambda cloud beta"
  },
  {
    "id": "3674df44-c7c0-405b-9c5c-29530c6b38c2",
    "created_at": "2024-10-19T23:52:10.116Z",
    "updated_at": "2023-02-05T23:56:35.722Z",
    "user_id": "93d6fc35-a3f2-4c17-aacb-929aa6aa2fc5",
    "school_id": "e79eff17-079c-460e-9a26-f6b16b4cabdd",
    "module_slug": "Module cloud module gamma jumps kappa epsilon brown 43",
    "module_category": "Dog client data",
    "is_started": false,
    "started_at": "2023-10-27T04:03:11.118Z",
    "is_completed": true,
    "completed_at": "2023-05-08T03:39:44.434Z",
    "sections_completed": 4612,
    "total_sections": 43590,
    "current_section": 2831,
    "time_spent_minutes": 6607,
    "is_bookmarked": true,
    "bookmarked_at": "2024-02-24T08:41:42.296Z",
    "user_notes": "Sigma system sigma server gamma theta gamma delta",
    "metadata": "Zeta module omega"
  },
  {
    "id": "478f272c-eebd-4250-be67-d9991ce9f31e",
    "created_at": "2024-01-31T08:32:33.033Z",
    "updated_at": "2024-06-07T21:10:45.679Z",
    "user_id": "311ed5e5-7033-4f3a-8522-bc4773e4b14a",
    "school_id": "d1e20847-18b5-4dd4-b591-dea6f83b635a",
    "module_slug": "Data sigma theta kappa sigma alpha lazy the 44",
    "module_category": "Network platform delta",
    "is_started": true,
    "started_at": "2024-05-29T10:59:41.177Z",
    "is_completed": true,
    "completed_at": "2023-09-13T15:57:27.335Z",
    "sections_completed": 8010,
    "total_sections": 61577,
    "current_section": 1686,
    "time_spent_minutes": 9086,
    "is_bookmarked": false,
    "bookmarked_at": "2023-01-25T12:11:14.503Z",
    "user_notes": "Over zeta kappa platform fox platform dog client",
    "metadata": "Dog gamma data"
  },
  {
    "id": "64400f3b-31dd-4119-ac37-0e58bb5e2390",
    "created_at": "2024-10-27T12:10:23.489Z",
    "updated_at": "2023-08-10T04:15:57.207Z",
    "user_id": "247af781-380e-4990-bdc8-d5f1a622363d",
    "school_id": "e63ae94b-1898-4c17-ade8-2906c177e61b",
    "module_slug": "Lazy cloud brown omega sigma jumps platform the 45",
    "module_category": "Omega process brown",
    "is_started": false,
    "started_at": "2024-09-29T03:40:57.047Z",
    "is_completed": true,
    "completed_at": "2024-01-01T07:06:26.704Z",
    "sections_completed": 8934,
    "total_sections": 69439,
    "current_section": 7312,
    "time_spent_minutes": 5402,
    "is_bookmarked": true,
    "bookmarked_at": "2023-09-03T16:02:31.852Z",
    "user_notes": "Omega service quick network epsilon client lambda quick",
    "metadata": "Module module delta"
  },
  {
    "id": "557c4217-4c3f-4880-b545-be5558f34b1d",
    "created_at": "2023-09-24T20:36:15.357Z",
    "updated_at": "2024-01-26T07:28:26.261Z",
    "user_id": "5bfc38b4-3be7-442c-90e9-c79914036e71",
    "school_id": "6a2807e4-3c6c-40cb-a83a-947f8f0d0f9c",
    "module_slug": "Gamma engine zeta network lambda alpha platform brown 46",
    "module_category": "Dog cloud client",
    "is_started": true,
    "started_at": "2023-11-21T14:02:35.779Z",
    "is_completed": false,
    "completed_at": "2024-07-13T18:13:11.857Z",
    "sections_completed": 5742,
    "total_sections": 72482,
    "current_section": 1958,
    "time_spent_minutes": 8615,
    "is_bookmarked": false,
    "bookmarked_at": "2024-06-09T12:46:51.130Z",
    "user_notes": "Delta brown data sigma quick sigma cloud alpha",
    "metadata": "Kappa gamma zeta"
  },
  {
    "id": "83dbd68e-affe-4e85-9906-109aaf9029d9",
    "created_at": "2024-09-04T19:36:55.500Z",
    "updated_at": "2024-11-16T07:07:15.326Z",
    "user_id": "431a5b40-2048-4f3c-8be1-4f5051034b34",
    "school_id": "709fecf1-4c2c-45fd-b242-0c5a6e35f9c5",
    "module_slug": "Lazy kappa network sigma server dog quick omega 47",
    "module_category": "Theta module sigma",
    "is_started": true,
    "started_at": "2023-09-30T04:59:44.884Z",
    "is_completed": true,
    "completed_at": "2024-11-19T01:07:29.640Z",
    "sections_completed": 6581,
    "total_sections": 13622,
    "current_section": 1822,
    "time_spent_minutes": 5650,
    "is_bookmarked": false,
    "bookmarked_at": "2024-07-03T22:00:16.092Z",
    "user_notes": "Client dog alpha omega module gamma alpha alpha",
    "metadata": "Network cloud platform"
  },
  {
    "id": "7d41c477-ffc2-420a-b5da-14437139467e",
    "created_at": "2023-08-13T00:15:58.670Z",
    "updated_at": "2024-11-15T09:53:16.782Z",
    "user_id": "9e960472-64ad-4619-93b1-10133b3710a7",
    "school_id": "a76eba8c-cf6c-40c2-a2a0-1e8a044e9d6d",
    "module_slug": "Dog zeta process delta server service alpha lambda 48",
    "module_category": "Sigma system over",
    "is_started": true,
    "started_at": "2024-03-15T10:07:38.734Z",
    "is_completed": false,
    "completed_at": "2023-10-02T08:16:17.371Z",
    "sections_completed": 1279,
    "total_sections": 62593,
    "current_section": 1448,
    "time_spent_minutes": 17,
    "is_bookmarked": true,
    "bookmarked_at": "2023-01-14T09:48:12.391Z",
    "user_notes": "Omega zeta jumps engine quick data beta dog",
    "metadata": "Beta alpha lambda"
  },
  {
    "id": "7067e872-3f72-4437-b0be-3df3232f2ee6",
    "created_at": "2023-05-15T00:01:44.363Z",
    "updated_at": "2024-06-21T23:12:22.514Z",
    "user_id": "76543ae0-464c-4d65-a572-139795bbbdb8",
    "school_id": "1da2e8b3-b68b-4d22-a3ab-d7db4b2e932b",
    "module_slug": "Service beta client lazy process client client fox 49",
    "module_category": "Process process kappa",
    "is_started": false,
    "started_at": "2024-10-13T05:44:55.902Z",
    "is_completed": false,
    "completed_at": "2024-12-29T02:27:40.906Z",
    "sections_completed": 4157,
    "total_sections": 59666,
    "current_section": 3933,
    "time_spent_minutes": 201,
    "is_bookmarked": true,
    "bookmarked_at": "2024-06-02T05:36:25.554Z",
    "user_notes": "Cloud lazy kappa over platform alpha process lambda",
    "metadata": "Data gamma omega"
  },
  {
    "id": "d16dfb2d-f084-4360-942b-c20400a2c025",
    "created_at": "2024-04-24T16:24:58.307Z",
    "updated_at": "2024-01-14T06:51:17.682Z",
    "user_id": "a3ac05b6-03cd-4cc9-a028-054b5b79b736",
    "school_id": "7ea58e42-0ef4-405d-bc8c-27051340dfc4",
    "module_slug": "Module epsilon system epsilon network beta quick lambda 50",
    "module_category": "Module epsilon sigma",
    "is_started": true,
    "started_at": "2024-04-13T10:03:52.532Z",
    "is_completed": true,
    "completed_at": "2024-03-06T15:33:22.283Z",
    "sections_completed": 7619,
    "total_sections": 43233,
    "current_section": 9536,
    "time_spent_minutes": 9699,
    "is_bookmarked": false,
    "bookmarked_at": "2024-08-23T10:54:35.851Z",
    "user_notes": "Module sigma epsilon kappa omega over omega alpha",
    "metadata": "Brown the jumps"
  }
]