[
  {
    "id": "f2a5ad08-4a61-4b46-955c-32f680485c61",
    "created_at": "2024-10-04T21:05:02.967Z",
    "school_id": "3af9dfb1-e827-411b-9522-0a15eb841c7a",
    "data_source_id": "c953688e-8cce-499c-aa82-57c54e507268",
    "sync_type": "Brown beta theta gamma kappa module cloud beta",
    "started_at": "2024-10-31T07:19:01.687Z",
    "completed_at": "2024-10-30T08:02:24.236Z",
    "status": "active",
    "error_message": "Network lambda over sigma module brown kappa gamma",
    "records_processed": 8821,
    "records_created": 7066,
    "records_updated": 8680,
    "records_deleted": 6880,
    "records_skipped": 1891,
    "details": "Process omega the",
    "errors": "The over data",
    "triggered_by": "Kappa server fox process client alpha network alpha",
    "triggered_by_user_id": "dce75c11-8356-4cfe-bd48-27e699de5b3a",
    "duration_ms": 519
  },
  {
    "id": "374a7e02-7d60-4afe-a456-83079e3e6329",
    "created_at": "2024-09-03T11:43:49.357Z",
    "school_id": "429b932b-2da1-4334-9a53-418a74bae2bb",
    "data_source_id": "0552f89b-d09d-4e8f-82f7-8c656b193cd6",
    "sync_type": "Over lazy brown module alpha gamma data zeta",
    "started_at": "2024-06-21T12:28:03.915Z",
    "completed_at": "2023-03-01T07:31:44.632Z",
    "status": "active",
    "error_message": "Zeta quick over brown fox system module platform",
    "records_processed": 941,
    "records_created": 5161,
    "records_updated": 8234,
    "records_deleted": 8650,
    "records_skipped": 9703,
    "details": "Lambda service platform",
    "errors": "Quick platform network",
    "triggered_by": "Delta engine dog beta data gamma engine client",
    "triggered_by_user_id": "247af781-380e-4990-bdc8-d5f1a622363d",
    "duration_ms": 1003
  },
  {
    "id": "d4bc912b-1a14-4dfb-816a-4594e95c24cc",
    "created_at": "2023-05-16T13:26:43.670Z",
    "school_id": "d1e20847-18b5-4dd4-b591-dea6f83b635a",
    "data_source_id": "ee2e2fc6-fc1e-42f4-ad16-215d6510f3e2",
    "sync_type": "Service theta alpha service zeta beta epsilon brown",
    "started_at": "2023-08-03T13:36:57.630Z",
    "completed_at": "2023-01-07T18:25:08.264Z",
    "status": "inactive",
    "error_message": "The lazy service fox delta brown over zeta",
    "records_processed": 9923,
    "records_created": 7544,
    "records_updated": 9975,
    "records_deleted": 7842,
    "records_skipped": 6474,
    "details": "Zeta system data",
    "errors": "Client over lazy",
    "triggered_by": "Brown zeta fox sigma epsilon omega cloud platform",
    "triggered_by_user_id": "256d52d9-02cd-4cdd-bbff-d4c496410840",
    "duration_ms": 6650
  },
  {
    "id": "2711140d-fbc0-4eac-89e9-a352c37f5a76",
    "created_at": "2024-11-09T12:14:16.454Z",
    "school_id": "b0770ed7-4c12-4e57-b236-e7fea0d23424",
    "data_source_id": "3e7fccb2-b2a9-422e-98c3-a1417eeb5b55",
    "sync_type": "Fox beta beta network system jumps jumps over",
    "started_at": "2023-07-06T17:41:47.506Z",
    "completed_at": "2023-07-30T10:17:51.942Z",
    "status": "active",
    "error_message": "Process server dog brown epsilon alpha cloud system",
    "records_processed": 1775,
    "records_created": 3445,
    "records_updated": 2236,
    "records_deleted": 184,
    "records_skipped": 5239,
    "details": "Theta fox module",
    "errors": "Platform network system",
    "triggered_by": "Beta zeta theta brown alpha server sigma dog",
    "triggered_by_user_id": "5bfc38b4-3be7-442c-90e9-c79914036e71",
    "duration_ms": 2782
  },
  {
    "id": "20c86b6e-7bef-4b75-9f7b-78fc9473eef4",
    "created_at": "2023-09-05T08:19:26.263Z",
    "school_id": "d72f8446-14ba-40ec-99f7-43228ea077d8",
    "data_source_id": "9e9f7fd7-163b-4881-acec-982582dcf2ad",
    "sync_type": "The dog kappa client alpha fox lambda lambda",
    "started_at": "2024-04-02T08:26:11.965Z",
    "completed_at": "2024-07-17T03:55:32.741Z",
    "status": "active",
    "error_message": "Fox gamma network gamma the dog network quick",
    "records_processed": 4647,
    "records_created": 2296,
    "records_updated": 6185,
    "records_deleted": 1794,
    "records_skipped": 5118,
    "details": "Jumps alpha delta",
    "errors": "Fox omega lazy",
    "triggered_by": "Data epsilon lambda dog epsilon fox dog service",
    "triggered_by_user_id": "53031b80-974a-46fc-a146-c37e7c5b5844",
    "duration_ms": 1429
  },
  {
    "id": "0d892327-28b7-4c42-9340-ea75e643c42f",
    "created_at": "2024-01-21T05:54:10.286Z",
    "school_id": "d1e20847-18b5-4dd4-b591-dea6f83b635a",
    "data_source_id": "a2a335c1-5f79-455b-84d2-88e97fdfebc4",
    "sync_type": "Brown zeta theta brown lambda alpha omega platform",
    "started_at": "2024-08-08T17:24:58.763Z",
    "completed_at": "2023-08-11T09:54:55.536Z",
    "status": "active",
    "error_message": "Data sigma beta process over system lazy lambda",
    "records_processed": 2234,
    "records_created": 9046,
    "records_updated": 1479,
    "records_deleted": 2575,
    "records_skipped": 3140,
    "details": "Cloud zeta fox",
    "errors": "Server brown gamma",
    "triggered_by": "Over dog data alpha module client data module",
    "triggered_by_user_id": "93d6fc35-a3f2-4c17-aacb-929aa6aa2fc5",
    "duration_ms": 7202
  },
  {
    "id": "c7f49668-5906-4671-849d-47efd50d3ee7",
    "created_at": "2024-03-31T06:53:26.750Z",
    "school_id": "a22f4242-5c63-4c92-b09b-3a83acf9e2e4",
    "data_source_id": "acdd8776-0705-45eb-b0bb-522178b9647b",
    "sync_type": "Beta process kappa jumps fox alpha fox sigma",
    "started_at": "2024-01-04T12:25:35.178Z",
    "completed_at": "2024-03-06T03:32:00.831Z",
    "status": "active",
    "error_message": "System network engine kappa quick sigma lazy engine",
    "records_processed": 6247,
    "records_created": 4245,
    "records_updated": 9832,
    "records_deleted": 8877,
    "records_skipped": 9938,
    "details": "Delta engine system",
    "errors": "Sigma sigma server",
    "triggered_by": "Quick network module client module process delta quick",
    "triggered_by_user_id": "68a7b7c2-d0de-4752-af9a-260157f65f43",
    "duration_ms": 7234
  },
  {
    "id": "f004d966-7f26-4d26-998a-1c5e80a9d083",
    "created_at": "2023-04-01T15:46:47.744Z",
    "school_id": "7f1a6162-0c95-498f-b977-567d263d0836",
    "data_source_id": "ff363804-4c7e-4cf0-9688-42ba63a476b5",
    "sync_type": "Kappa beta delta theta the quick fox epsilon",
    "started_at": "2023-06-14T11:38:21.265Z",
    "completed_at": "2023-02-24T07:49:42.080Z",
    "status": "inactive",
    "error_message": "Brown gamma platform kappa gamma platform zeta service",
    "records_processed": 3692,
    "records_created": 7970,
    "records_updated": 3484,
    "records_deleted": 9163,
    "records_skipped": 5928,
    "details": "Engine network data",
    "errors": "Fox theta process",
    "triggered_by": "Over engine lambda service engine zeta quick gamma",
    "triggered_by_user_id": "431a5b40-2048-4f3c-8be1-4f5051034b34",
    "duration_ms": 3915
  },
  {
    "id": "e1b2a852-aaf0-4226-b643-2c01c50d681a",
    "created_at": "2024-07-29T11:15:10.561Z",
    "school_id": "a2d512c8-9dab-45a5-8ef7-2a9ab335bdc5",
    "data_source_id": "65c130df-2faf-473f-8638-7a86891eb3f6",
    "sync_type": "Module network kappa lazy the dog omega network",
    "started_at": "2023-02-08T20:00:23.732Z",
    "completed_at": "2024-11-05T15:02:41.479Z",
    "status": "active",
    "error_message": "System zeta zeta alpha system over epsilon the",
    "records_processed": 3790,
    "records_created": 1743,
    "records_updated": 3938,
    "records_deleted": 2168,
    "records_skipped": 7009,
    "details": "Sigma theta alpha",
    "errors": "Kappa delta platform",
    "triggered_by": "Quick brown alpha brown service the omega kappa",
    "triggered_by_user_id": "ded464d7-7fbc-41d9-b600-1f5a934a99a8",
    "duration_ms": 4488
  },
  {
    "id": "80132294-63ac-454b-addd-97715db582ce",
    "created_at": "2024-02-05T21:43:24.344Z",
    "school_id": "a22f4242-5c63-4c92-b09b-3a83acf9e2e4",
    "data_source_id": "f94ecb58-2fac-4ea4-a051-f0dcceaf0ed0",
    "sync_type": "Delta omega fox beta kappa service client gamma",
    "started_at": "2023-04-24T21:51:27.912Z",
    "completed_at": "2024-10-18T05:04:28.438Z",
    "status": "pending",
    "error_message": "Alpha the omega client quick kappa the engine",
    "records_processed": 4667,
    "records_created": 8744,
    "records_updated": 847,
    "records_deleted": 3561,
    "records_skipped": 3442,
    "details": "Module kappa zeta",
    "errors": "Engine service epsilon",
    "triggered_by": "Over delta omega client jumps data over theta",
    "triggered_by_user_id": "247af781-380e-4990-bdc8-d5f1a622363d",
    "duration_ms": 5759
  },
  {
    "id": "7307b49c-11e2-4ffc-bb0f-375a36f8194c",
    "created_at": "2024-01-22T14:56:28.742Z",
    "school_id": "72862cd1-b7dc-4fe1-a248-87852f1474d5",
    "data_source_id": "ee2e2fc6-fc1e-42f4-ad16-215d6510f3e2",
    "sync_type": "Zeta fox over fox omega gamma cloud quick",
    "started_at": "2024-04-18T20:52:52.245Z",
    "completed_at": "2023-03-16T01:34:13.840Z",
    "status": "active",
    "error_message": "Fox zeta network over process fox service dog",
    "records_processed": 4414,
    "records_created": 3747,
    "records_updated": 5764,
    "records_deleted": 8906,
    "records_skipped": 7192,
    "details": "Lambda service engine",
    "errors": "Quick service epsilon",
    "triggered_by": "Platform server theta dog data zeta omega beta",
    "triggered_by_user_id": "77409a2e-fa26-4040-ab51-b054a6d62520",
    "duration_ms": 2383
  },
  {
    "id": "ec163d43-8e43-498e-9aca-aa3ead0909f0",
    "created_at": "2023-05-22T09:47:47.059Z",
    "school_id": "a76eba8c-cf6c-40c2-a2a0-1e8a044e9d6d",
    "data_source_id": "7e44aaff-9440-4df7-8e30-14b1b89f44c3",
    "sync_type": "Fox fox beta platform process kappa system network",
    "started_at": "2024-10-30T04:10:49.816Z",
    "completed_at": "2024-10-05T19:19:13.486Z",
    "status": "active",
    "error_message": "Client system lazy zeta server epsilon system service",
    "records_processed": 8089,
    "records_created": 5524,
    "records_updated": 1462,
    "records_deleted": 2474,
    "records_skipped": 7498,
    "details": "Fox gamma over",
    "errors": "Platform omega client",
    "triggered_by": "Sigma alpha engine data dog gamma cloud over",
    "triggered_by_user_id": "6ca09ad2-b75d-4118-87fe-5e6a9f9232b8",
    "duration_ms": 7044
  },
  {
    "id": "5be66c3e-3ab5-4701-ba9d-b202a08f5c77",
    "created_at": "2024-12-28T20:43:59.774Z",
    "school_id": "302e57f3-f396-4a47-a165-7dcc583d2e9b",
    "data_source_id": "a2a335c1-5f79-455b-84d2-88e97fdfebc4",
    "sync_type": "Server over platform server gamma service the system",
    "started_at": "2024-09-04T04:11:25.416Z",
    "completed_at": "2023-03-14T00:18:12.190Z",
    "status": "active",
    "error_message": "Gamma over beta the jumps network delta quick",
    "records_processed": 3101,
    "records_created": 9710,
    "records_updated": 1673,
    "records_deleted": 1590,
    "records_skipped": 2463,
    "details": "Theta omega delta",
    "errors": "Jumps network delta",
    "triggered_by": "Sigma lambda cloud alpha quick lazy process jumps",
    "triggered_by_user_id": "ded464d7-7fbc-41d9-b600-1f5a934a99a8",
    "duration_ms": 6288
  },
  {
    "id": "c381cd02-c6bc-49cd-b70f-44daa7519287",
    "created_at": "2023-12-20T15:22:12.334Z",
    "school_id": "3ba5f8eb-68c8-4e45-9dfa-9c18cb043f51",
    "data_source_id": "c953688e-8cce-499c-aa82-57c54e507268",
    "sync_type": "Delta platform dog kappa quick epsilon lambda epsilon",
    "started_at": "2023-12-11T11:37:18.488Z",
    "completed_at": "2024-10-11T10:20:49.670Z",
    "status": "active",
    "error_message": "Zeta kappa the theta theta module beta over",
    "records_processed": 1434,
    "records_created": 8589,
    "records_updated": 4793,
    "records_deleted": 5658,
    "records_skipped": 7627,
    "details": "Zeta quick gamma",
    "errors": "Lazy brown kappa",
    "triggered_by": "Engine network the quick quick server module service",
    "triggered_by_user_id": "76543ae0-464c-4d65-a572-139795bbbdb8",
    "duration_ms": 2030
  },
  {
    "id": "a5ad0132-5daa-4a51-a986-8ea6a64e469c",
    "created_at": "2024-01-03T05:22:50.273Z",
    "school_id": "a2d512c8-9dab-45a5-8ef7-2a9ab335bdc5",
    "data_source_id": "407efde5-de3e-489b-af9b-904a70cdeaff",
    "sync_type": "Service jumps quick theta fox omega client brown",
    "started_at": "2023-01-18T13:47:24.731Z",
    "completed_at": "2024-08-13T05:06:01.537Z",
    "status": "active",
    "error_message": "Alpha engine network dog platform lazy sigma fox",
    "records_processed": 7761,
    "records_created": 73,
    "records_updated": 879,
    "records_deleted": 830,
    "records_skipped": 6081,
    "details": "Data the beta",
    "errors": "Brown process fox",
    "triggered_by": "Delta kappa the the system theta engine alpha",
    "triggered_by_user_id": "ce67985f-24c5-4c89-b6ca-4ba33ee65661",
    "duration_ms": 4221
  },
  {
    "id": "f6439d68-4c5d-4331-9c75-702490eada29",
    "created_at": "2023-12-27T06:06:10.591Z",
    "school_id": "3ba5f8eb-68c8-4e45-9dfa-9c18cb043f51",
    "data_source_id": "752bfdf2-04b9-418b-ad22-e11f121785b3",
    "sync_type": "Delta platform module lambda network zeta epsilon kappa",
    "started_at": "2024-11-06T04:47:29.894Z",
    "completed_at": "2024-10-17T14:26:04.795Z",
    "status": "active",
    "error_message": "Kappa kappa omega lambda over theta omega fox",
    "records_processed": 4939,
    "records_created": 3250,
    "records_updated": 5161,
    "records_deleted": 1192,
    "records_skipped": 3921,
    "details": "Dog kappa beta",
    "errors": "Gamma delta process",
    "triggered_by": "System omega dog client network dog zeta over",
    "triggered_by_user_id": "8c5b218d-7074-4cb8-8a0a-d17c40ee60a7",
    "duration_ms": 3077
  },
  {
    "id": "b6f1eaf0-a1b6-46e5-b573-3e94e727695f",
    "created_at": "2023-09-30T11:33:14.697Z",
    "school_id": "55f58b84-25ab-4e23-a8a2-52cad13d54df",
    "data_source_id": "4f081014-037c-46c0-8591-e8921ea07859",
    "sync_type": "Dog process dog service beta beta cloud lambda",
    "started_at": "2024-12-21T13:16:51.324Z",
    "completed_at": "2024-04-14T10:35:53.771Z",
    "status": "pending",
    "error_message": "Jumps process server dog lambda platform sigma process",
    "records_processed": 8276,
    "records_created": 8368,
    "records_updated": 3422,
    "records_deleted": 8601,
    "records_skipped": 5514,
    "details": "Module system kappa",
    "errors": "Process network dog",
    "triggered_by": "Network gamma system dog system alpha gamma sigma",
    "triggered_by_user_id": "4d44215c-0371-4549-8935-0da42e2492a9",
    "duration_ms": 2212
  },
  {
    "id": "5a3096b4-fe40-474a-8db8-2903fd6904fe",
    "created_at": "2023-01-02T21:49:42.803Z",
    "school_id": "ca622101-e857-428f-bbf6-3cff8789d201",
    "data_source_id": "65c130df-2faf-473f-8638-7a86891eb3f6",
    "sync_type": "Jumps kappa omega fox service server process delta",
    "started_at": "2023-05-06T03:42:43.412Z",
    "completed_at": "2023-07-20T09:01:45.633Z",
    "status": "active",
    "error_message": "Kappa fox quick omega theta data gamma network",
    "records_processed": 7578,
    "records_created": 722,
    "records_updated": 4307,
    "records_deleted": 3740,
    "records_skipped": 5937,
    "details": "The lazy client",
    "errors": "Network epsilon beta",
    "triggered_by": "Jumps lambda omega over lambda brown module omega",
    "triggered_by_user_id": "68a7b7c2-d0de-4752-af9a-260157f65f43",
    "duration_ms": 6674
  },
  {
    "id": "9c2f28e6-68e5-473e-81e6-f709b73bc6fd",
    "created_at": "2024-02-02T07:34:02.933Z",
    "school_id": "3ba5f8eb-68c8-4e45-9dfa-9c18cb043f51",
    "data_source_id": "5824518f-9bf3-4dcb-b2e0-02b4a30cc81e",
    "sync_type": "Service cloud cloud module delta omega brown lambda",
    "started_at": "2023-01-23T00:33:24.916Z",
    "completed_at": "2024-09-25T12:21:55.759Z",
    "status": "active",
    "error_message": "Beta delta server system epsilon gamma zeta over",
    "records_processed": 7529,
    "records_created": 3715,
    "records_updated": 7221,
    "records_deleted": 1748,
    "records_skipped": 332,
    "details": "Quick gamma lazy",
    "errors": "Kappa engine alpha",
    "triggered_by": "Cloud brown client lazy quick process fox platform",
    "triggered_by_user_id": "77409a2e-fa26-4040-ab51-b054a6d62520",
    "duration_ms": 6957
  },
  {
    "id": "8da0b13d-3434-4867-b850-d9a07524c753",
    "created_at": "2024-04-04T20:44:33.669Z",
    "school_id": "51447bfd-fb7b-49bb-8117-0624e086e562",
    "data_source_id": "86ad6027-de52-4642-9916-c71eaca54730",
    "sync_type": "Kappa client theta lazy data the system process",
    "started_at": "2024-02-25T20:40:47.561Z",
    "completed_at": "2024-03-10T18:26:51.439Z",
    "status": "active",
    "error_message": "Kappa over delta jumps jumps lambda omega quick",
    "records_processed": 2435,
    "records_created": 5136,
    "records_updated": 8766,
    "records_deleted": 8006,
    "records_skipped": 415,
    "details": "Client delta fox",
    "errors": "Lazy service engine",
    "triggered_by": "Server epsilon data over sigma delta the platform",
    "triggered_by_user_id": "a5076835-a146-407a-95fc-0c07e3ae44a8",
    "duration_ms": 7556
  },
  {
    "id": "ceaa5bb2-81ab-43db-98bd-e9c108deec28",
    "created_at": "2023-03-12T12:28:17.925Z",
    "school_id": "55f58b84-25ab-4e23-a8a2-52cad13d54df",
    "data_source_id": "4f081014-037c-46c0-8591-e8921ea07859",
    "sync_type": "Cloud quick engine lazy zeta zeta gamma delta",
    "started_at": "2024-12-24T01:57:42.925Z",
    "completed_at": "2024-03-09T11:22:14.957Z",
    "status": "active",
    "error_message": "Client zeta server platform client platform kappa quick",
    "records_processed": 541,
    "records_created": 6420,
    "records_updated": 733,
    "records_deleted": 6985,
    "records_skipped": 1607,
    "details": "Over jumps epsilon",
    "errors": "Client delta network",
    "triggered_by": "Gamma service fox engine server system kappa data",
    "triggered_by_user_id": "ea65d9c9-c9e0-4af9-9aef-2a2ec0fd37f4",
    "duration_ms": 7803
  },
  {
    "id": "2e2787d5-2701-4ba2-9102-8c7a47436bfb",
    "created_at": "2023-02-26T02:43:54.440Z",
    "school_id": "a76eba8c-cf6c-40c2-a2a0-1e8a044e9d6d",
    "data_source_id": "06f0c016-8729-4b41-89fb-cce6aaa27d13",
    "sync_type": "Network platform gamma lazy omega brown omega fox",
    "started_at": "2023-12-30T10:59:27.144Z",
    "completed_at": "2023-11-26T21:47:46.941Z",
    "status": "active",
    "error_message": "Module server lambda epsilon server gamma process fox",
    "records_processed": 5839,
    "records_created": 7458,
    "records_updated": 7564,
    "records_deleted": 6236,
    "records_skipped": 1223,
    "details": "Epsilon kappa omega",
    "errors": "Fox kappa zeta",
    "triggered_by": "Beta process theta kappa data engine fox process",
    "triggered_by_user_id": "6ca09ad2-b75d-4118-87fe-5e6a9f9232b8",
    "duration_ms": 8306
  },
  {
    "id": "afc441b5-eded-462d-aee4-fd1084f4987f",
    "created_at": "2024-02-10T03:58:23.430Z",
    "school_id": "a2d512c8-9dab-45a5-8ef7-2a9ab335bdc5",
    "data_source_id": "d1d79765-afc1-4e19-8fc3-dc993a3d2f06",
    "sync_type": "Dog brown engine epsilon zeta fox beta engine",
    "started_at": "2023-10-18T19:35:34.566Z",
    "completed_at": "2023-11-11T21:54:15.592Z",
    "status": "active",
    "error_message": "Process engine beta zeta system module brown epsilon",
    "records_processed": 5474,
    "records_created": 791,
    "records_updated": 9759,
    "records_deleted": 5849,
    "records_skipped": 3693,
    "details": "Platform platform fox",
    "errors": "Jumps process over",
    "triggered_by": "Module the fox module zeta fox fox service",
    "triggered_by_user_id": "dce75c11-8356-4cfe-bd48-27e699de5b3a",
    "duration_ms": 3853
  },
  {
    "id": "2a35845e-41af-4808-a4d3-9a1fb1912037",
    "created_at": "2023-06-08T00:04:09.169Z",
    "school_id": "7f1a6162-0c95-498f-b977-567d263d0836",
    "data_source_id": "c8829aba-6269-4171-9825-8c4c49c0db88",
    "sync_type": "Fox alpha service fox network system sigma theta",
    "started_at": "2023-12-08T19:52:39.409Z",
    "completed_at": "2024-04-12T05:14:32.766Z",
    "status": "inactive",
    "error_message": "Platform system kappa beta kappa sigma process dog",
    "records_processed": 1672,
    "records_created": 2486,
    "records_updated": 7169,
    "records_deleted": 250,
    "records_skipped": 9122,
    "details": "Brown process client",
    "errors": "Gamma gamma alpha",
    "triggered_by": "Cloud sigma the jumps quick service lambda module",
    "triggered_by_user_id": "9a894605-ddea-41dd-a462-196c6628fe61",
    "duration_ms": 4560
  },
  {
    "id": "597f6750-758e-47f3-80b1-76d3c7361345",
    "created_at": "2024-02-29T01:38:54.071Z",
    "school_id": "6c2d5ecd-fa0e-4caf-bc6d-92cd359d8540",
    "data_source_id": "e38301dd-21e1-4497-a86a-9bb17b9132da",
    "sync_type": "The alpha dog omega theta platform lambda server",
    "started_at": "2024-10-23T06:17:05.312Z",
    "completed_at": "2024-09-13T23:12:54.911Z",
    "status": "pending",
    "error_message": "Zeta engine omega delta beta over service server",
    "records_processed": 3042,
    "records_created": 8394,
    "records_updated": 1018,
    "records_deleted": 4531,
    "records_skipped": 7846,
    "details": "Network quick lazy",
    "errors": "Beta platform network",
    "triggered_by": "Lambda zeta zeta engine omega jumps gamma sigma",
    "triggered_by_user_id": "93d6fc35-a3f2-4c17-aacb-929aa6aa2fc5",
    "duration_ms": 5353
  },
  {
    "id": "80c2be9e-57db-4599-b3c0-3612c5aeb242",
    "created_at": "2023-01-07T07:28:14.469Z",
    "school_id": "5991e55d-5f96-47f4-a5e8-124df35b4f31",
    "data_source_id": "cc6d81d1-331b-4844-8840-2a48c7175720",
    "sync_type": "Beta cloud quick module zeta jumps quick quick",
    "started_at": "2023-07-11T23:17:31.502Z",
    "completed_at": "2024-10-27T17:46:53.042Z",
    "status": "active",
    "error_message": "Client network engine client platform module brown dog",
    "records_processed": 5255,
    "records_created": 4938,
    "records_updated": 6867,
    "records_deleted": 7701,
    "records_skipped": 9583,
    "details": "Gamma lambda fox",
    "errors": "Server over network",
    "triggered_by": "Brown beta the sigma quick alpha the jumps",
    "triggered_by_user_id": "9a894605-ddea-41dd-a462-196c6628fe61",
    "duration_ms": 1410
  },
  {
    "id": "9bb66cb3-1631-41a5-ae32-6f3123b44829",
    "created_at": "2023-04-28T20:12:39.357Z",
    "school_id": "a8414277-0b30-44cc-82f6-fa46c4b1eb54",
    "data_source_id": "407efde5-de3e-489b-af9b-904a70cdeaff",
    "sync_type": "Gamma delta over beta data jumps fox fox",
    "started_at": "2024-05-06T03:29:38.878Z",
    "completed_at": "2023-06-09T21:49:52.784Z",
    "status": "inactive",
    "error_message": "Quick jumps omega system sigma dog beta dog",
    "records_processed": 8129,
    "records_created": 3173,
    "records_updated": 9658,
    "records_deleted": 1363,
    "records_skipped": 8617,
    "details": "Lazy epsilon epsilon",
    "errors": "Brown alpha lazy",
    "triggered_by": "Module epsilon cloud gamma the data system over",
    "triggered_by_user_id": "6cd587fc-8a79-47ca-875c-d813acfd99a0",
    "duration_ms": 9708
  },
  {
    "id": "c9376f1c-ca5c-4896-899b-75ad2d0d8b9b",
    "created_at": "2024-05-27T18:09:25.335Z",
    "school_id": "3af9dfb1-e827-411b-9522-0a15eb841c7a",
    "data_source_id": "d43686c4-d0b4-4c54-85ee-d30791210624",
    "sync_type": "Lazy service service jumps data omega beta over",
    "started_at": "2023-01-25T08:45:59.847Z",
    "completed_at": "2024-06-22T13:41:46.245Z",
    "status": "active",
    "error_message": "Omega server alpha zeta dog delta cloud platform",
    "records_processed": 7733,
    "records_created": 6695,
    "records_updated": 101,
    "records_deleted": 9767,
    "records_skipped": 7683,
    "details": "Beta brown network",
    "errors": "Delta gamma cloud",
    "triggered_by": "Over cloud quick omega process dog engine delta",
    "triggered_by_user_id": "53031b80-974a-46fc-a146-c37e7c5b5844",
    "duration_ms": 6684
  },
  {
    "id": "403c2453-af6b-4bd2-ab62-a1e27b5d9b2a",
    "created_at": "2023-01-04T02:26:36.699Z",
    "school_id": "1da2e8b3-b68b-4d22-a3ab-d7db4b2e932b",
    "data_source_id": "099dbb67-a6b6-43eb-ab56-eee14e063f37",
    "sync_type": "The client gamma client process engine service server",
    "started_at": "2023-02-09T01:14:22.079Z",
    "completed_at": "2024-04-09T00:09:31.989Z",
    "status": "inactive",
    "error_message": "Data beta module jumps epsilon engine platform cloud",
    "records_processed": 7090,
    "records_created": 3615,
    "records_updated": 4345,
    "records_deleted": 7139,
    "records_skipped": 1645,
    "details": "Client zeta module",
    "errors": "Dog system over",
    "triggered_by": "Beta jumps the zeta zeta cloud client lazy",
    "triggered_by_user_id": "a10e1f0e-342b-4a00-824e-0709f6de5dab",
    "duration_ms": 6776
  },
  {
    "id": "665b29f0-974e-4bc7-84bf-9a30369908cb",
    "created_at": "2024-01-04T13:43:14.817Z",
    "school_id": "1da2e8b3-b68b-4d22-a3ab-d7db4b2e932b",
    "data_source_id": "4b69cf36-3004-4248-a582-7377730e909f",
    "sync_type": "Platform alpha jumps process lambda service system module",
    "started_at": "2023-06-25T05:02:08.634Z",
    "completed_at": "2024-02-06T16:23:32.147Z",
    "status": "active",
    "error_message": "Client lazy client service epsilon network dog quick",
    "records_processed": 518,
    "records_created": 5638,
    "records_updated": 6793,
    "records_deleted": 8518,
    "records_skipped": 9840,
    "details": "Cloud zeta kappa",
    "errors": "Quick beta data",
    "triggered_by": "Sigma quick sigma omega beta server brown gamma",
    "triggered_by_user_id": "4d44215c-0371-4549-8935-0da42e2492a9",
    "duration_ms": 3426
  },
  {
    "id": "67d2e334-4d73-42f9-853c-aeddb70d4df2",
    "created_at": "2023-08-20T19:30:43.724Z",
    "school_id": "709fecf1-4c2c-45fd-b242-0c5a6e35f9c5",
    "data_source_id": "5824518f-9bf3-4dcb-b2e0-02b4a30cc81e",
    "sync_type": "Over server sigma delta alpha alpha delta omega",
    "started_at": "2023-04-15T17:05:13.438Z",
    "completed_at": "2023-11-17T07:23:29.432Z",
    "status": "inactive",
    "error_message": "Client kappa fox over network epsilon server alpha",
    "records_processed": 4946,
    "records_created": 2021,
    "records_updated": 1555,
    "records_deleted": 3795,
    "records_skipped": 41,
    "details": "Network fox gamma",
    "errors": "Client kappa cloud",
    "triggered_by": "Engine delta sigma data network service dog omega",
    "triggered_by_user_id": "518d95c8-c2ef-46a7-8d08-652647fd8726",
    "duration_ms": 191
  },
  {
    "id": "bc0a042e-c83d-45b9-b547-509b47414374",
    "created_at": "2024-03-29T22:10:26.229Z",
    "school_id": "36a66c02-6a0c-46da-ad01-970e20511e13",
    "data_source_id": "26ef89e0-595c-417b-a068-d8e4f8ec7787",
    "sync_type": "Theta over platform client module platform jumps engine",
    "started_at": "2023-12-14T11:01:30.800Z",
    "completed_at": "2024-11-23T05:20:39.103Z",
    "status": "active",
    "error_message": "The process sigma engine data lambda sigma lambda",
    "records_processed": 6708,
    "records_created": 5644,
    "records_updated": 8369,
    "records_deleted": 6923,
    "records_skipped": 8759,
    "details": "Network module fox",
    "errors": "System omega system",
    "triggered_by": "Server epsilon brown omega over process epsilon dog",
    "triggered_by_user_id": "9a894605-ddea-41dd-a462-196c6628fe61",
    "duration_ms": 8773
  },
  {
    "id": "7d672939-ad9a-4190-a822-89516bcf01c8",
    "created_at": "2023-06-13T19:27:02.851Z",
    "school_id": "72862cd1-b7dc-4fe1-a248-87852f1474d5",
    "data_source_id": "d43686c4-d0b4-4c54-85ee-d30791210624",
    "sync_type": "Over jumps over sigma cloud epsilon dog lazy",
    "started_at": "2023-08-13T05:11:32.859Z",
    "completed_at": "2023-11-18T23:22:24.665Z",
    "status": "inactive",
    "error_message": "Client kappa lazy server zeta over theta beta",
    "records_processed": 9554,
    "records_created": 7240,
    "records_updated": 4218,
    "records_deleted": 1284,
    "records_skipped": 9355,
    "details": "Beta the delta",
    "errors": "The network client",
    "triggered_by": "Client alpha module alpha lambda sigma sigma system",
    "triggered_by_user_id": "77409a2e-fa26-4040-ab51-b054a6d62520",
    "duration_ms": 5481
  },
  {
    "id": "462b06b3-9470-4bda-be57-9b3e5bba8e0f",
    "created_at": "2024-01-15T12:31:22.858Z",
    "school_id": "49871cfe-155b-4956-9609-038c92155cdd",
    "data_source_id": "c0e245ba-42d1-47ad-bd80-7a9048865159",
    "sync_type": "Omega zeta beta data data theta engine jumps",
    "started_at": "2023-12-04T09:20:28.168Z",
    "completed_at": "2024-12-30T18:26:44.451Z",
    "status": "active",
    "error_message": "Process network omega client gamma alpha gamma omega",
    "records_processed": 8891,
    "records_created": 6643,
    "records_updated": 3017,
    "records_deleted": 2504,
    "records_skipped": 3012,
    "details": "The data module",
    "errors": "Process data kappa",
    "triggered_by": "Cloud platform alpha over dog delta the alpha",
    "triggered_by_user_id": "1015b7f4-6153-4501-9ea0-e0480ec4eece",
    "duration_ms": 6049
  },
  {
    "id": "30722840-e8f0-42c1-a5b0-6548e1a9e7c5",
    "created_at": "2023-10-26T15:30:10.090Z",
    "school_id": "6aac852e-0d0b-4cf0-86f4-d1925de39350",
    "data_source_id": "86ad6027-de52-4642-9916-c71eaca54730",
    "sync_type": "Brown server quick kappa lazy kappa process dog",
    "started_at": "2024-03-07T01:35:54.048Z",
    "completed_at": "2023-07-03T22:58:17.132Z",
    "status": "active",
    "error_message": "Engine alpha system beta fox fox process alpha",
    "records_processed": 5190,
    "records_created": 2459,
    "records_updated": 371,
    "records_deleted": 4982,
    "records_skipped": 5664,
    "details": "Alpha service client",
    "errors": "Theta brown kappa",
    "triggered_by": "Zeta network lambda client alpha engine quick platform",
    "triggered_by_user_id": "247af781-380e-4990-bdc8-d5f1a622363d",
    "duration_ms": 839
  },
  {
    "id": "ed36f5ed-ea86-4fe0-a1a7-3d9c97562e8c",
    "created_at": "2024-11-17T11:29:36.795Z",
    "school_id": "ca622101-e857-428f-bbf6-3cff8789d201",
    "data_source_id": "06f0c016-8729-4b41-89fb-cce6aaa27d13",
    "sync_type": "Server cloud server beta server lazy the service",
    "started_at": "2023-01-29T23:33:50.976Z",
    "completed_at": "2024-09-25T02:13:17.851Z",
    "status": "active",
    "error_message": "Alpha quick sigma zeta system brown delta system",
    "records_processed": 5716,
    "records_created": 4680,
    "records_updated": 2078,
    "records_deleted": 6836,
    "records_skipped": 3743,
    "details": "System epsilon system",
    "errors": "Engine beta epsilon",
    "triggered_by": "Fox process process sigma lazy delta dog gamma",
    "triggered_by_user_id": "4464c5fc-c1be-4bbc-9368-dc6cf5cb9193",
    "duration_ms": 2148
  },
  {
    "id": "b18fd79c-8522-444c-b28e-0e9240180c23",
    "created_at": "2023-07-24T04:50:49.441Z",
    "school_id": "fa4a14da-1fca-487a-823a-bb45fa95e2aa",
    "data_source_id": "099dbb67-a6b6-43eb-ab56-eee14e063f37",
    "sync_type": "Service dog service fox theta beta jumps alpha",
    "started_at": "2024-04-02T18:53:17.380Z",
    "completed_at": "2023-07-13T11:01:25.894Z",
    "status": "active",
    "error_message": "Theta lambda brown fox cloud the omega service",
    "records_processed": 9392,
    "records_created": 4149,
    "records_updated": 3994,
    "records_deleted": 5720,
    "records_skipped": 2981,
    "details": "Delta dog service",
    "errors": "Gamma gamma data",
    "triggered_by": "Fox quick the theta over lambda jumps brown",
    "triggered_by_user_id": "8e35b5b3-3e98-4ec0-a694-2856d78a055b",
    "duration_ms": 7263
  },
  {
    "id": "e069ac78-93f6-4579-af68-7afdd0ac843d",
    "created_at": "2024-01-31T02:22:28.833Z",
    "school_id": "72862cd1-b7dc-4fe1-a248-87852f1474d5",
    "data_source_id": "697dba15-410a-4f18-9058-ad52283567cb",
    "sync_type": "Fox epsilon over system data zeta kappa epsilon",
    "started_at": "2023-09-03T14:39:16.306Z",
    "completed_at": "2023-06-20T06:56:47.370Z",
    "status": "active",
    "error_message": "Alpha delta platform theta server zeta process over",
    "records_processed": 920,
    "records_created": 1859,
    "records_updated": 5413,
    "records_deleted": 4558,
    "records_skipped": 4209,
    "details": "Sigma engine client",
    "errors": "Delta over alpha",
    "triggered_by": "The server process epsilon system theta platform quick",
    "triggered_by_user_id": "8e35b5b3-3e98-4ec0-a694-2856d78a055b",
    "duration_ms": 2785
  },
  {
    "id": "c70f0348-06cc-4239-b89f-faa1774b6deb",
    "created_at": "2024-08-26T16:30:05.657Z",
    "school_id": "72862cd1-b7dc-4fe1-a248-87852f1474d5",
    "data_source_id": "c0c1fe2d-b171-42f6-b317-b62acde93f64",
    "sync_type": "Quick service fox zeta brown alpha process theta",
    "started_at": "2024-01-12T12:26:39.370Z",
    "completed_at": "2024-06-20T22:54:24.802Z",
    "status": "active",
    "error_message": "Gamma over client alpha theta client gamma zeta",
    "records_processed": 5476,
    "records_created": 7307,
    "records_updated": 9091,
    "records_deleted": 2865,
    "records_skipped": 1924,
    "details": "Engine omega client",
    "errors": "Client theta theta",
    "triggered_by": "Sigma engine client quick client alpha quick data",
    "triggered_by_user_id": "6090c86d-d922-4d47-96db-1835cf3bf57e",
    "duration_ms": 7658
  },
  {
    "id": "a4d52e1b-624b-4606-af26-8989b595a9c3",
    "created_at": "2024-12-02T14:32:08.797Z",
    "school_id": "7f1a6162-0c95-498f-b977-567d263d0836",
    "data_source_id": "f9bd77b1-2b1a-49c3-b835-e17025e4745b",
    "sync_type": "Cloud process process zeta engine over fox gamma",
    "started_at": "2024-06-30T20:45:28.467Z",
    "completed_at": "2023-09-03T18:15:46.211Z",
    "status": "active",
    "error_message": "The process dog module quick sigma zeta dog",
    "records_processed": 6326,
    "records_created": 1285,
    "records_updated": 7916,
    "records_deleted": 320,
    "records_skipped": 4996,
    "details": "Fox system lambda",
    "errors": "Brown server service",
    "triggered_by": "Cloud server delta brown the data cloud fox",
    "triggered_by_user_id": "f7c14361-afba-457f-90e6-2cb012c03d91",
    "duration_ms": 7394
  },
  {
    "id": "04a0a673-3198-4fc2-8e69-c70b2efdd4d6",
    "created_at": "2024-01-02T07:00:20.108Z",
    "school_id": "51447bfd-fb7b-49bb-8117-0624e086e562",
    "data_source_id": "9264160d-796a-4673-b621-c33618ef966b",
    "sync_type": "System service cloud network gamma fox engine omega",
    "started_at": "2023-01-12T20:50:28.974Z",
    "completed_at": "2024-05-20T18:09:59.182Z",
    "status": "pending",
    "error_message": "The zeta kappa server dog service delta over",
    "records_processed": 7771,
    "records_created": 961,
    "records_updated": 114,
    "records_deleted": 6381,
    "records_skipped": 7083,
    "details": "Platform the cloud",
    "errors": "Engine quick module",
    "triggered_by": "Epsilon platform system zeta network the fox server",
    "triggered_by_user_id": "a10e1f0e-342b-4a00-824e-0709f6de5dab",
    "duration_ms": 2214
  },
  {
    "id": "8d555aa1-0700-434b-bbeb-a62da7a68152",
    "created_at": "2023-12-02T08:03:58.146Z",
    "school_id": "cf9e6ad5-c02b-4a41-9f72-9d6eb615983f",
    "data_source_id": "cc6d81d1-331b-4844-8840-2a48c7175720",
    "sync_type": "Sigma server delta lambda zeta server cloud gamma",
    "started_at": "2024-09-22T08:56:39.041Z",
    "completed_at": "2024-01-14T18:50:55.810Z",
    "status": "active",
    "error_message": "Beta lambda gamma data data epsilon delta service",
    "records_processed": 8743,
    "records_created": 4740,
    "records_updated": 5245,
    "records_deleted": 939,
    "records_skipped": 4644,
    "details": "Engine the dog",
    "errors": "Fox omega client",
    "triggered_by": "The sigma network beta delta jumps kappa brown",
    "triggered_by_user_id": "1015b7f4-6153-4501-9ea0-e0480ec4eece",
    "duration_ms": 9347
  },
  {
    "id": "3642c547-03de-4abe-a210-d04754a91005",
    "created_at": "2023-12-15T00:52:38.341Z",
    "school_id": "5991e55d-5f96-47f4-a5e8-124df35b4f31",
    "data_source_id": "dddbc7d1-ef70-42b2-a8b1-3b8978c9784a",
    "sync_type": "Epsilon server cloud service epsilon delta delta dog",
    "started_at": "2024-07-25T07:45:05.586Z",
    "completed_at": "2024-12-19T05:59:42.301Z",
    "status": "active",
    "error_message": "Dog fox omega system quick dog client theta",
    "records_processed": 1232,
    "records_created": 7176,
    "records_updated": 7156,
    "records_deleted": 3128,
    "records_skipped": 191,
    "details": "Beta brown data",
    "errors": "Epsilon zeta data",
    "triggered_by": "System dog data omega data server service service",
    "triggered_by_user_id": "256d52d9-02cd-4cdd-bbff-d4c496410840",
    "duration_ms": 989
  },
  {
    "id": "ffeadf6a-a22c-4dbb-8ebb-5799b9d158d1",
    "created_at": "2024-03-04T02:41:01.583Z",
    "school_id": "49871cfe-155b-4956-9609-038c92155cdd",
    "data_source_id": "f94ecb58-2fac-4ea4-a051-f0dcceaf0ed0",
    "sync_type": "Delta service brown module beta platform over alpha",
    "started_at": "2024-04-03T12:42:35.338Z",
    "completed_at": "2024-11-17T01:24:41.821Z",
    "status": "active",
    "error_message": "Client server module engine client engine alpha zeta",
    "records_processed": 5877,
    "records_created": 1560,
    "records_updated": 9741,
    "records_deleted": 7140,
    "records_skipped": 8417,
    "details": "Gamma epsilon engine",
    "errors": "The system beta",
    "triggered_by": "Theta gamma client over client quick epsilon lambda",
    "triggered_by_user_id": "ea65d9c9-c9e0-4af9-9aef-2a2ec0fd37f4",
    "duration_ms": 7684
  },
  {
    "id": "60a1470d-4374-454d-94b9-acb46c86b696",
    "created_at": "2024-05-20T01:47:19.836Z",
    "school_id": "cf9e6ad5-c02b-4a41-9f72-9d6eb615983f",
    "data_source_id": "26ef89e0-595c-417b-a068-d8e4f8ec7787",
    "sync_type": "Epsilon omega platform gamma jumps dog beta network",
    "started_at": "2023-07-04T17:39:16.186Z",
    "completed_at": "2024-07-08T04:59:16.146Z",
    "status": "pending",
    "error_message": "Alpha service over data process jumps cloud zeta",
    "records_processed": 6394,
    "records_created": 2340,
    "records_updated": 6539,
    "records_deleted": 2069,
    "records_skipped": 2441,
    "details": "Dog theta over",
    "errors": "Zeta module service",
    "triggered_by": "Module theta cloud the the kappa system kappa",
    "triggered_by_user_id": "a3ac05b6-03cd-4cc9-a028-054b5b79b736",
    "duration_ms": 6599
  },
  {
    "id": "fad79826-db4b-4efa-8b0c-3064153433cc",
    "created_at": "2023-09-17T00:26:07.814Z",
    "school_id": "6a2807e4-3c6c-40cb-a83a-947f8f0d0f9c",
    "data_source_id": "4f081014-037c-46c0-8591-e8921ea07859",
    "sync_type": "Module over lambda dog process process quick process",
    "started_at": "2024-08-30T06:18:58.865Z",
    "completed_at": "2024-06-03T13:40:18.120Z",
    "status": "active",
    "error_message": "Kappa dog server kappa the system service process",
    "records_processed": 5018,
    "records_created": 2925,
    "records_updated": 8329,
    "records_deleted": 7676,
    "records_skipped": 7030,
    "details": "Fox server omega",
    "errors": "Gamma service quick",
    "triggered_by": "Process network zeta over system jumps zeta data",
    "triggered_by_user_id": "53031b80-974a-46fc-a146-c37e7c5b5844",
    "duration_ms": 4579
  },
  {
    "id": "3862f531-6a15-43df-8f0f-834688aace62",
    "created_at": "2023-11-22T07:11:41.211Z",
    "school_id": "b0770ed7-4c12-4e57-b236-e7fea0d23424",
    "data_source_id": "752bfdf2-04b9-418b-ad22-e11f121785b3",
    "sync_type": "Omega zeta brown module zeta platform quick module",
    "started_at": "2024-04-13T18:30:03.745Z",
    "completed_at": "2023-08-05T23:45:40.903Z",
    "status": "active",
    "error_message": "Fox service omega beta beta server gamma process",
    "records_processed": 5365,
    "records_created": 7118,
    "records_updated": 5527,
    "records_deleted": 6196,
    "records_skipped": 9320,
    "details": "Data module system",
    "errors": "Gamma theta engine",
    "triggered_by": "Dog quick kappa brown client brown brown sigma",
    "triggered_by_user_id": "c19199c3-cf21-45b1-92f2-8523a68eb34e",
    "duration_ms": 549
  },
  {
    "id": "c059a6b1-2a9e-432c-be51-8c4806bbe456",
    "created_at": "2023-11-27T03:46:46.303Z",
    "school_id": "95d56d72-c51f-4111-bdc3-b3a7dc6033e0",
    "data_source_id": "4f081014-037c-46c0-8591-e8921ea07859",
    "sync_type": "Dog lazy gamma client server fox alpha delta",
    "started_at": "2023-08-03T14:17:44.739Z",
    "completed_at": "2024-06-09T10:15:35.932Z",
    "status": "active",
    "error_message": "Beta fox platform platform module zeta theta quick",
    "records_processed": 5170,
    "records_created": 7912,
    "records_updated": 7371,
    "records_deleted": 737,
    "records_skipped": 5449,
    "details": "Network engine over",
    "errors": "Process zeta omega",
    "triggered_by": "Engine system delta jumps system system dog kappa",
    "triggered_by_user_id": "4d44215c-0371-4549-8935-0da42e2492a9",
    "duration_ms": 6978
  },
  {
    "id": "c779b790-0da6-4dcd-90fa-4001b7039694",
    "created_at": "2023-02-22T10:29:58.463Z",
    "school_id": "a2d512c8-9dab-45a5-8ef7-2a9ab335bdc5",
    "data_source_id": "62bd39b8-f625-4488-8677-38f83f9bc79e",
    "sync_type": "Delta server module sigma process engine jumps data",
    "started_at": "2023-04-06T07:11:32.548Z",
    "completed_at": "2023-07-01T16:04:40.948Z",
    "status": "active",
    "error_message": "Zeta engine alpha delta beta delta client network",
    "records_processed": 4764,
    "records_created": 4815,
    "records_updated": 1685,
    "records_deleted": 559,
    "records_skipped": 965,
    "details": "System dog kappa",
    "errors": "Cloud sigma dog",
    "triggered_by": "Alpha dog jumps over alpha zeta the zeta",
    "triggered_by_user_id": "8c5b218d-7074-4cb8-8a0a-d17c40ee60a7",
    "duration_ms": 8379
  },
  {
    "id": "4c22460c-beaf-44ef-a241-c9c35c132bb3",
    "created_at": "2024-09-08T13:06:18.892Z",
    "school_id": "429b932b-2da1-4334-9a53-418a74bae2bb",
    "data_source_id": "2f87cbcd-5136-467c-82e1-e87527ed79f3",
    "sync_type": "Client sigma client alpha zeta gamma data cloud",
    "started_at": "2023-01-21T02:26:26.957Z",
    "completed_at": "2024-09-09T11:54:00.902Z",
    "status": "pending",
    "error_message": "Data gamma alpha over over service dog omega",
    "records_processed": 7066,
    "records_created": 7999,
    "records_updated": 4352,
    "records_deleted": 3343,
    "records_skipped": 8716,
    "details": "Cloud beta network",
    "errors": "Client fox module",
    "triggered_by": "Dog process jumps the jumps zeta zeta beta",
    "triggered_by_user_id": "a3ac05b6-03cd-4cc9-a028-054b5b79b736",
    "duration_ms": 7322
  }
]