[
  {
    "id": "651c3347-6720-490f-8d97-31393dcf7229",
    "location_code": "Brown zeta theta clo",
    "location_name": "Service delta server network epsilon theta lazy epsilon",
    "location_type": "Zeta platform the over dog eng",
    "building": "Dog omega engine fox sigma network lambda brown",
    "floor_level": 8673,
    "room_number": "Zeta data zeta lambd",
    "capacity": 7289,
    "is_active": true,
    "qr_code_data": "Kappa epsilon omega beta delta brown theta kappa",
    "created_at": "2024-04-20T06:40:10.849Z"
  },
  {
    "id": "492bf64e-ff29-4fed-a1a6-6aedaa6dc680",
    "location_code": "Sigma brown system p",
    "location_name": "Client system alpha process alpha client gamma server",
    "location_type": "Zeta kappa gamma lambda zeta t",
    "building": "Theta service sigma omega fox quick cloud server",
    "floor_level": 7720,
    "room_number": "Process omega system",
    "capacity": 7166,
    "is_active": false,
    "qr_code_data": "Quick engine server alpha process alpha over data",
    "created_at": "2024-11-04T11:02:16.191Z"
  },
  {
    "id": "b8798d62-7ca7-4227-90ec-b41c4b991701",
    "location_code": "Fox network beta eps",
    "location_name": "Kappa gamma delta lambda data omega kappa omega",
    "location_type": "Server process brown service b",
    "building": "Quick beta omega delta module gamma delta platform",
    "floor_level": 833,
    "room_number": "Kappa dog the zeta k",
    "capacity": 3505,
    "is_active": false,
    "qr_code_data": "Delta module sigma kappa quick jumps beta gamma",
    "created_at": "2024-06-12T01:40:03.903Z"
  },
  {
    "id": "e2f3921f-c6f0-4e05-b590-8cab7d8b1b15",
    "location_code": "Gamma sigma theta pl",
    "location_name": "Beta dog server fox sigma cloud service fox",
    "location_type": "Alpha server quick sigma lazy ",
    "building": "Brown alpha platform alpha jumps the client module",
    "floor_level": 1682,
    "room_number": "Network service thet",
    "capacity": 389,
    "is_active": false,
    "qr_code_data": "Fox module engine brown zeta the data alpha",
    "created_at": "2023-10-01T22:32:30.793Z"
  },
  {
    "id": "f46dcfcf-f2a1-4430-bfb6-7e4c9f6d8628",
    "location_code": "Zeta kappa lambda om",
    "location_name": "Epsilon delta over system network gamma system data",
    "location_type": "Dog sigma omega network servic",
    "building": "Omega delta theta service module server delta proc",
    "floor_level": 5492,
    "room_number": "Lazy alpha process c",
    "capacity": 8753,
    "is_active": false,
    "qr_code_data": "Alpha client sigma omega lambda epsilon kappa service",
    "created_at": "2024-06-13T07:12:19.405Z"
  },
  {
    "id": "82874fb7-2cdf-43dc-b2f5-35a64797bee5",
    "location_code": "Service server cloud",
    "location_name": "Beta zeta platform lazy client client platform platform",
    "location_type": "Cloud beta dog zeta epsilon th",
    "building": "Module server over zeta server network delta omega",
    "floor_level": 7871,
    "room_number": "Server quick dog sys",
    "capacity": 5221,
    "is_active": false,
    "qr_code_data": "Jumps the fox process gamma quick platform dog",
    "created_at": "2023-03-29T21:21:53.951Z"
  },
  {
    "id": "a8ade0ee-da3e-4056-93a4-cb6204fae68a",
    "location_code": "Lazy service dog the",
    "location_name": "Sigma dog theta fox server the beta kappa",
    "location_type": "Cloud epsilon epsilon server c",
    "building": "The brown lazy data omega brown fox client",
    "floor_level": 4453,
    "room_number": "Engine kappa kappa d",
    "capacity": 9032,
    "is_active": true,
    "qr_code_data": "Cloud service quick theta service over gamma network",
    "created_at": "2024-03-24T20:10:27.980Z"
  },
  {
    "id": "059fe291-a1d9-4850-b7ac-093e9fd91a7d",
    "location_code": "Process client modul",
    "location_name": "System quick epsilon network lazy fox brown process",
    "location_type": "Gamma epsilon jumps delta jump",
    "building": "Lazy platform service module network cloud network",
    "floor_level": 7612,
    "room_number": "Beta kappa quick del",
    "capacity": 468,
    "is_active": true,
    "qr_code_data": "Beta lazy kappa beta over sigma omega system",
    "created_at": "2024-04-20T20:57:39.270Z"
  },
  {
    "id": "a1003b56-49d6-4db0-b148-e903825076ed",
    "location_code": "Client cloud epsilon",
    "location_name": "Omega dog beta lambda lambda sigma sigma jumps",
    "location_type": "Jumps data cloud client fox cl",
    "building": "Fox platform data network module theta platform do",
    "floor_level": 7973,
    "room_number": "Data zeta data engin",
    "capacity": 1511,
    "is_active": true,
    "qr_code_data": "Sigma system epsilon beta process over delta the",
    "created_at": "2023-03-12T00:53:23.094Z"
  },
  {
    "id": "1cbc32cf-7429-48e5-81a9-7a44f545f259",
    "location_code": "Client brown service",
    "location_name": "Over data system network system theta data client",
    "location_type": "Epsilon server engine module s",
    "building": "Omega alpha fox epsilon jumps client lazy delta",
    "floor_level": 5408,
    "room_number": "Network theta kappa ",
    "capacity": 1931,
    "is_active": true,
    "qr_code_data": "Beta brown alpha theta platform omega platform delta",
    "created_at": "2023-03-05T06:45:29.378Z"
  },
  {
    "id": "6242fd82-f564-4eac-b532-575b1467cac4",
    "location_code": "Jumps delta service ",
    "location_name": "System module module beta service delta server quick",
    "location_type": "Gamma brown platform system ze",
    "building": "Network sigma engine kappa network alpha platform ",
    "floor_level": 8732,
    "room_number": "Service lambda sigma",
    "capacity": 2197,
    "is_active": false,
    "qr_code_data": "Cloud system dog network lambda network client alpha",
    "created_at": "2023-05-13T06:50:56.295Z"
  },
  {
    "id": "212fa628-4140-4f64-b2d4-8fae19d8f04c",
    "location_code": "Process process dog ",
    "location_name": "The kappa jumps service over beta module epsilon",
    "location_type": "Process client data sigma serv",
    "building": "Server over cloud omega dog system alpha kappa",
    "floor_level": 9333,
    "room_number": "Dog quick jumps sigm",
    "capacity": 9535,
    "is_active": false,
    "qr_code_data": "Client client network over lambda data over quick",
    "created_at": "2024-10-25T21:01:49.377Z"
  },
  {
    "id": "a6e92ada-9dad-4e37-a7b0-7a323ac7e3d7",
    "location_code": "Process kappa theta ",
    "location_name": "Lazy engine module server the omega the platform",
    "location_type": "Theta platform theta lazy dog ",
    "building": "Data jumps omega client service over network over",
    "floor_level": 5213,
    "room_number": "Client system proces",
    "capacity": 9257,
    "is_active": false,
    "qr_code_data": "Over quick client brown theta epsilon delta alpha",
    "created_at": "2023-03-13T06:36:46.372Z"
  },
  {
    "id": "3eeddfd3-a3e6-4b00-a736-eb1972b73af0",
    "location_code": "Lazy delta zeta fox ",
    "location_name": "Sigma beta module network lambda gamma theta fox",
    "location_type": "Kappa module network data zeta",
    "building": "Service server lazy platform module beta data netw",
    "floor_level": 3299,
    "room_number": "Epsilon kappa fox se",
    "capacity": 2609,
    "is_active": true,
    "qr_code_data": "Fox brown quick zeta over fox jumps zeta",
    "created_at": "2023-09-18T22:23:39.251Z"
  },
  {
    "id": "010ce2c0-e9dd-497e-be0a-aa0e9921de1f",
    "location_code": "Alpha lazy delta lam",
    "location_name": "Client process dog cloud service delta cloud zeta",
    "location_type": "Jumps module fox module data s",
    "building": "Platform system lambda omega quick lambda the lamb",
    "floor_level": 7955,
    "room_number": "Cloud gamma platform",
    "capacity": 2545,
    "is_active": false,
    "qr_code_data": "Data service the zeta service data epsilon module",
    "created_at": "2023-10-16T13:41:41.795Z"
  },
  {
    "id": "c50c4d07-8d76-46c4-a540-51f71da4ead7",
    "location_code": "Omega lazy zeta jump",
    "location_name": "System server gamma lambda sigma process server kappa",
    "location_type": "Data the theta server server t",
    "building": "Dog client omega sigma lazy module lazy platform",
    "floor_level": 1816,
    "room_number": "Over cloud lambda de",
    "capacity": 397,
    "is_active": false,
    "qr_code_data": "Over alpha module gamma fox jumps module system",
    "created_at": "2024-12-17T02:08:08.450Z"
  },
  {
    "id": "3e09910a-888e-43f7-9b00-ccd238c6c09c",
    "location_code": "Alpha data beta serv",
    "location_name": "Server theta client server omega quick sigma system",
    "location_type": "Over zeta kappa the lazy gamma",
    "building": "Zeta system brown delta zeta network lambda gamma",
    "floor_level": 1671,
    "room_number": "Data theta over epsi",
    "capacity": 1857,
    "is_active": true,
    "qr_code_data": "Kappa dog client lazy platform engine fox fox",
    "created_at": "2024-03-31T10:11:05.698Z"
  },
  {
    "id": "e5d75c9d-98a6-4587-89ae-e80a668c6f6c",
    "location_code": "Client delta zeta cl",
    "location_name": "Brown epsilon server module network epsilon client lazy",
    "location_type": "Service client brown zeta over",
    "building": "Platform brown lambda client service engine module",
    "floor_level": 9797,
    "room_number": "Quick module sigma f",
    "capacity": 5858,
    "is_active": false,
    "qr_code_data": "Sigma delta system gamma alpha epsilon theta beta",
    "created_at": "2024-08-26T04:22:52.218Z"
  },
  {
    "id": "e7d01105-826a-4084-86bf-0a3553ae5c79",
    "location_code": "Jumps kappa beta ove",
    "location_name": "System system network fox alpha theta fox lambda",
    "location_type": "Zeta omega engine quick theta ",
    "building": "Dog quick alpha cloud data brown network lazy",
    "floor_level": 9548,
    "room_number": "Process kappa jumps ",
    "capacity": 264,
    "is_active": false,
    "qr_code_data": "Kappa theta sigma platform system jumps alpha platform",
    "created_at": "2023-09-09T11:40:29.269Z"
  },
  {
    "id": "b209f36e-c6d7-446e-bdef-88fd2c777e38",
    "location_code": "Network brown jumps ",
    "location_name": "Over data cloud quick engine over platform fox",
    "location_type": "Brown jumps engine lambda clie",
    "building": "Brown delta quick fox service platform epsilon alp",
    "floor_level": 5367,
    "room_number": "Cloud network proces",
    "capacity": 281,
    "is_active": false,
    "qr_code_data": "Gamma client lambda fox fox server platform cloud",
    "created_at": "2023-02-15T21:34:13.352Z"
  },
  {
    "id": "518dbd60-3a59-47ac-ad1d-d579427c6e5c",
    "location_code": "Fox system the engin",
    "location_name": "System module dog epsilon system data alpha beta",
    "location_type": "Service engine epsilon platfor",
    "building": "Engine server quick network cloud network dog lazy",
    "floor_level": 9097,
    "room_number": "Sigma data module ju",
    "capacity": 805,
    "is_active": false,
    "qr_code_data": "Zeta alpha data the service kappa beta fox",
    "created_at": "2023-05-16T04:47:12.663Z"
  },
  {
    "id": "21b1a97d-097d-4a49-b082-90b5e15b133f",
    "location_code": "Client brown sigma e",
    "location_name": "Platform gamma lazy kappa the process zeta cloud",
    "location_type": "Lazy data brown network server",
    "building": "Quick omega lazy brown client platform kappa fox",
    "floor_level": 1562,
    "room_number": "Zeta data omega modu",
    "capacity": 2494,
    "is_active": true,
    "qr_code_data": "Service over kappa network theta process zeta dog",
    "created_at": "2023-07-02T02:32:46.513Z"
  },
  {
    "id": "5ecad6b2-c5de-4557-8fa7-fc44df78014c",
    "location_code": "Module theta sigma b",
    "location_name": "Gamma theta jumps server lazy lambda theta fox",
    "location_type": "Client cloud data the client l",
    "building": "Process epsilon engine engine theta client kappa d",
    "floor_level": 629,
    "room_number": "Epsilon module clien",
    "capacity": 3278,
    "is_active": false,
    "qr_code_data": "Brown theta zeta over delta client brown beta",
    "created_at": "2023-09-25T09:47:40.711Z"
  },
  {
    "id": "0fdf8e71-27c7-4b63-9142-efd2fc87b4f3",
    "location_code": "Cloud quick lazy ser",
    "location_name": "Quick client epsilon theta epsilon quick process platform",
    "location_type": "Kappa theta client engine dog ",
    "building": "Lambda process system sigma the cloud system proce",
    "floor_level": 1046,
    "room_number": "Module theta system ",
    "capacity": 6667,
    "is_active": true,
    "qr_code_data": "Lambda theta quick client module dog engine brown",
    "created_at": "2024-02-22T05:07:33.744Z"
  },
  {
    "id": "0b487f45-d17f-4f3a-9893-bab9f6000576",
    "location_code": "Omega omega fox proc",
    "location_name": "Kappa delta process zeta gamma lazy lambda platform",
    "location_type": "Delta theta platform alpha zet",
    "building": "Epsilon service gamma brown service delta theta ze",
    "floor_level": 3791,
    "room_number": "Fox brown process br",
    "capacity": 5754,
    "is_active": true,
    "qr_code_data": "Kappa network beta client cloud jumps system engine",
    "created_at": "2023-12-12T18:05:57.510Z"
  },
  {
    "id": "6a0fc45d-edf8-40b5-a1fc-a87309b232b3",
    "location_code": "Omega service kappa ",
    "location_name": "Kappa cloud service over jumps client zeta brown",
    "location_type": "Platform system lambda alpha s",
    "building": "Module data alpha brown engine zeta gamma epsilon",
    "floor_level": 2086,
    "room_number": "Engine alpha sigma e",
    "capacity": 1567,
    "is_active": true,
    "qr_code_data": "Delta dog beta kappa engine process brown sigma",
    "created_at": "2024-06-06T06:43:59.957Z"
  },
  {
    "id": "9f901795-6b62-44a7-9b3a-2c949eaf1983",
    "location_code": "Sigma jumps omega sy",
    "location_name": "Dog brown zeta quick process system system module",
    "location_type": "Lambda process quick the lambd",
    "building": "Lambda system lazy delta service lambda engine jum",
    "floor_level": 3436,
    "room_number": "Client process clien",
    "capacity": 3507,
    "is_active": true,
    "qr_code_data": "Server client fox gamma lazy alpha omega beta",
    "created_at": "2023-05-25T04:33:07.263Z"
  },
  {
    "id": "5f9c9c04-5766-4685-ab14-d192b24e8f73",
    "location_code": "Quick cloud system q",
    "location_name": "Dog beta brown theta zeta service lazy module",
    "location_type": "Gamma gamma theta lazy server ",
    "building": "Platform quick lambda gamma data sigma lazy beta",
    "floor_level": 6739,
    "room_number": "Dog theta theta clou",
    "capacity": 2755,
    "is_active": true,
    "qr_code_data": "Omega network quick process alpha platform theta client",
    "created_at": "2023-12-15T00:54:52.063Z"
  },
  {
    "id": "5b8e64e8-11c3-4b49-ad59-de53b342cfb8",
    "location_code": "Brown kappa kappa th",
    "location_name": "Quick cloud omega data sigma gamma network module",
    "location_type": "Kappa over over dog dog omega ",
    "building": "Over epsilon alpha jumps dog brown theta zeta",
    "floor_level": 2187,
    "room_number": "Zeta epsilon server ",
    "capacity": 1896,
    "is_active": true,
    "qr_code_data": "The omega the kappa module client gamma omega",
    "created_at": "2024-05-20T19:01:22.803Z"
  },
  {
    "id": "b147a51f-8bdb-4462-881b-b03e75996483",
    "location_code": "Client the delta del",
    "location_name": "Cloud network module omega sigma service omega service",
    "location_type": "Quick process data lambda delt",
    "building": "Network beta module kappa omega gamma the alpha",
    "floor_level": 7443,
    "room_number": "Service alpha alpha ",
    "capacity": 8654,
    "is_active": true,
    "qr_code_data": "Client gamma process brown theta cloud system jumps",
    "created_at": "2023-06-19T08:39:53.772Z"
  }
]